{"jobIds": ["044e258d-db30-412b-8453-6ee71087a765"], "results": [{"jobId": "044e258d-db30-412b-8453-6ee71087a765", "result": {"data": {"timestamp": "2025-01-28T07:05:29.922Z", "rootActivityId": "94880490-dfc0-4701-b49b-9214d2608bb4", "descriptor": {"Select": [{"Kind": 1, "Depth": 0, "Value": "G0", "GroupKeys": [{"Source": {"Entity": "Detail Report Trainee", "Property": "pkTraineeRegNumber"}, "Calc": "G0", "IsSameAsSelect": true}], "Name": "Detail Report Trainee.pkTraineeRegNumber"}, {"Kind": 1, "Depth": 0, "Value": "G1", "GroupKeys": [{"Source": {"Entity": "Detail Report Trainee", "Property": "TraineeFirstName"}, "Calc": "G1", "IsSameAsSelect": true}], "Name": "Detail Report Trainee.TraineeFirstName"}, {"Kind": 1, "Depth": 0, "Value": "G2", "GroupKeys": [{"Source": {"Entity": "Detail Report Trainee", "Property": "Gender"}, "Calc": "G2", "IsSameAsSelect": true}], "Name": "Detail Report Trainee.Gender"}, {"Kind": 1, "Depth": 0, "Value": "G3", "GroupKeys": [{"Source": {"Entity": "Detail Report Trainee", "Property": "FatherGuardianName"}, "Calc": "G3", "IsSameAsSelect": true}], "Name": "Detail Report Trainee.FatherGuardianName"}, {"Kind": 1, "Depth": 0, "Value": "G4", "GroupKeys": [{"Source": {"Entity": "Detail Report Trainee", "Property": "MotherName"}, "Calc": "G4", "IsSameAsSelect": true}], "Name": "Detail Report Trainee.MotherName"}, {"Kind": 1, "Depth": 0, "Value": "G5", "GroupKeys": [{"Source": {"Entity": "Trade", "Property": "Name"}, "Calc": "G5", "IsSameAsSelect": true}], "Name": "Trade.Name"}, {"Kind": 1, "Depth": 0, "Value": "G6", "GroupKeys": [{"Source": {"Entity": "Trade", "Property": "Course Duration"}, "Calc": "G6", "IsSameAsSelect": true}], "Name": "Trade.Course Duration"}, {"Kind": 1, "Depth": 0, "Value": "G7", "GroupKeys": [{"Source": {"Entity": "State", "Property": "StateName"}, "Calc": "G7", "IsSameAsSelect": true}], "Name": "State.StateName"}, {"Kind": 1, "Depth": 0, "Value": "G8", "GroupKeys": [{"Source": {"Entity": "District", "Property": "DistrictName"}, "Calc": "G8", "IsSameAsSelect": true}], "Name": "District.DistrictName"}, {"Kind": 1, "Depth": 0, "Value": "G9", "GroupKeys": [{"Source": {"Entity": "Category", "Property": "Category"}, "Calc": "G9", "IsSameAsSelect": true}], "Name": "Category.Category"}, {"Kind": 1, "Depth": 0, "Value": "G10", "GroupKeys": [{"Source": {"Entity": "Qualification", "Property": "Qualification"}, "Calc": "G10", "IsSameAsSelect": true}], "Name": "Qualification.Qualification"}, {"Kind": 1, "Depth": 0, "Value": "G11", "GroupKeys": [{"Source": {"Entity": "Trade", "Property": "Education Stream"}, "Calc": "G11", "IsSameAsSelect": true}], "Name": "Trade.Education Stream"}, {"Kind": 1, "Depth": 0, "Value": "G12", "GroupKeys": [{"Source": {"Entity": "ITI", "Property": "Name"}, "Calc": "G12", "IsSameAsSelect": true}], "Name": "ITI.Name"}, {"Kind": 1, "Depth": 0, "Value": "G13", "GroupKeys": [{"Source": {"Entity": "ITI", "Property": "ITICategory"}, "Calc": "G13", "IsSameAsSelect": true}], "Name": "ITI.ITICategory"}], "Expressions": {"Primary": {"Groupings": [{"Keys": [{"Source": {"Entity": "Detail Report Trainee", "Property": "pkTraineeRegNumber"}, "Select": 0}, {"Source": {"Entity": "Detail Report Trainee", "Property": "TraineeFirstName"}, "Select": 1}, {"Source": {"Entity": "Detail Report Trainee", "Property": "Gender"}, "Select": 2}, {"Source": {"Entity": "Detail Report Trainee", "Property": "FatherGuardianName"}, "Select": 3}, {"Source": {"Entity": "Detail Report Trainee", "Property": "MotherName"}, "Select": 4}, {"Source": {"Entity": "Trade", "Property": "Name"}, "Select": 5}, {"Source": {"Entity": "Trade", "Property": "Course Duration"}, "Select": 6}, {"Source": {"Entity": "State", "Property": "StateName"}, "Select": 7}, {"Source": {"Entity": "District", "Property": "DistrictName"}, "Select": 8}, {"Source": {"Entity": "Category", "Property": "Category"}, "Select": 9}, {"Source": {"Entity": "Qualification", "Property": "Qualification"}, "Select": 10}, {"Source": {"Entity": "Trade", "Property": "Education Stream"}, "Select": 11}, {"Source": {"Entity": "ITI", "Property": "Name"}, "Select": 12}, {"Source": {"Entity": "ITI", "Property": "ITICategory"}, "Select": 13}], "Member": "DM0"}]}}, "Version": 2}, "metrics": {"Version": "1.0.0", "Events": [{"Id": "f26419bc-a878-499c-8324-1ded198f25a9", "Name": "Execute Semantic Query", "Component": "DSE", "Start": "2025-01-28T07:05:29.9225228Z", "End": "2025-01-28T07:05:30.5631413Z"}, {"Id": "d0d9ede9-ad5d-430f-96b5-95feb77f57b1", "ParentId": "f26419bc-a878-499c-8324-1ded198f25a9", "Name": "Execute DAX Query", "Component": "DSE", "Start": "2025-01-28T07:05:29.9225228Z", "End": "2025-01-28T07:05:30.547525Z", "Metrics": {"RowCount": 1001}}, {"Id": "3C6BDE14-B99D-4C0E-B188-FD0C6F6238B1", "ParentId": "d0d9ede9-ad5d-430f-96b5-95feb77f57b1", "Name": "Execute Query", "Component": "AS", "Start": "2025-01-28T07:05:29.953Z", "End": "2025-01-28T07:05:30.553Z"}, {"Id": "70D4F9D4-DCAF-466F-965A-EC97A2DD5E11", "ParentId": "3C6BDE14-B99D-4C0E-B188-FD0C6F6238B1", "Name": "Serialize Rowset", "Component": "AS", "Start": "2025-01-28T07:05:30.55Z", "End": "2025-01-28T07:05:30.553Z"}]}, "fromCache": false, "dsr": {"Version": 2, "MinorVersion": 1, "DS": [{"N": "DS0", "PH": [{"DM0": [{"RF": 1, "S": [{"N": "G0", "T": 1, "DN": "D0"}, {"N": "G1", "T": 1, "DN": "D1"}, {"N": "G2", "T": 1, "DN": "D2"}, {"N": "G3", "T": 1, "DN": "D3"}, {"N": "G4", "T": 1, "DN": "D4"}, {"N": "G5", "T": 1, "DN": "D5"}, {"N": "G6", "T": 1, "DN": "D6"}, {"N": "G7", "T": 1, "DN": "D7"}, {"N": "G8", "T": 1, "DN": "D8"}, {"N": "G9", "T": 1, "DN": "D9"}, {"N": "G10", "T": 1, "DN": "D10"}, {"N": "G11", "T": 1, "DN": "D11"}, {"N": "G12", "T": 1, "DN": "D12"}, {"N": "G13", "T": 1, "DN": "D13"}], "C": [0, 0, 0, 0, 0, 0, 0, 0, 0, 0, 0, 0, 0, 0]}, {"C": [1, 1, 1, 1, 1], "R": 15844}, {"C": [2, 2, 2, 2, 1], "R": 16324}, {"C": [3, 3, 3, 3, 2], "R": 15844}, {"C": [4, 4, 1, 4, 4, 0], "R": 15840}, {"C": [5, 5, 0, 5, 5], "R": 16352}, {"C": [6, 6, 6, 6], "R": 16356}, {"C": [7, 7, 7, 7], "R": 16356}, {"C": [8, 8, 8, 8], "R": 16356}, {"C": [9, 9, 9, 9], "R": 16356}, {"C": [10, 10, 10, 10], "R": 16356}, {"C": [11, 11, 11, 11], "R": 16356}, {"C": [12, 12, 12, 12, 2, 1], "R": 16260}, {"C": [13, 13, 13, 13], "R": 16356}, {"C": [14, 14, 14, 14], "R": 16356}, {"C": [15, 15, 15, 15], "R": 16356}, {"C": [16, 7, 16, 16, 1], "R": 15844}, {"C": [17, 16, 17, 17], "R": 16356}, {"C": [18, 17, 18, 18], "R": 16356}, {"C": [19, 18, 1, 19, 19, 0], "R": 15840}, {"C": [20, 19, 0, 20, 20, 2], "R": 15840}, {"C": [21, 20, 21, 21], "R": 16356}, {"C": [22, 21, 22, 22], "R": 16356}, {"C": [23, 22, 23, 23, 0], "R": 15844}, {"C": [24, 23, 24, 24], "R": 16356}, {"C": [25, 24, 25, 25], "R": 16356}, {"C": [26, 25, 1, 26, 26], "R": 16352}, {"C": [27, 26, 0, 27, 27], "R": 16352}, {"C": [28, 27, 28, 28, 3, 0], "R": 16260}, {"C": [29, 28, 29, 18, 1], "R": 15844}, {"C": [30, 29, 30, 29, 0], "R": 15844}, {"C": [31, 30, 31, 30], "R": 16356}, {"C": [32, 31, 32, 31, 2], "R": 15844}, {"C": [33, 32, 33, 32, 0], "R": 15844}, {"C": [34, 33, 34, 33], "R": 16356}, {"C": [35, 34, 35, 34], "R": 16356}, {"C": [36, 35, 36, 35, 1], "R": 15844}, {"C": [37, 36, 37, 36, 4, 1, 0], "R": 15748}, {"C": [38, 10, 38, 34], "R": 16356}, {"C": [39, 37, 39, 37, 5, 0], "R": 16260}, {"C": [40, 38, 40, 38], "R": 16356}, {"C": [41, 39, 41, 36, 3], "R": 15844}, {"C": [42, 40, 42, 39, 0], "R": 15844}, {"C": [43, 41, 43, 40, 2], "R": 15844}, {"C": [44, 42, 44, 26, 0], "R": 15844}, {"C": [45, 43, 45, 41, 2], "R": 15844}, {"C": [46, 30, 46, 42, 0], "R": 15844}, {"C": [47, 44, 4, 43], "R": 16356}, {"C": [48, 45, 47, 44], "R": 16356}, {"C": [49, 46, 1, 48, 38], "R": 16352}, {"C": [50, 47, 0, 49, 45, 1], "R": 15840}, {"C": [51, 48, 50, 46, 0], "R": 15844}, {"C": [52, 1, 51, 47, 1], "R": 15844}, {"C": [53, 49, 52, 45], "R": 16356}, {"C": [54, 50, 53, 13], "R": 16356}, {"C": [55, 10, 44, 48, 0], "R": 15844}, {"C": [56, 51, 54, 11], "R": 16356}, {"C": [57, 52, 55, 49, 1], "R": 15844}, {"C": [58, 53, 56, 38], "R": 16356}, {"C": [59, 54, 1, 5, 50, 0], "R": 15840}, {"C": [60, 55, 0, 57, 51], "R": 16352}, {"C": [61, 56, 58, 52], "R": 16356}, {"C": [62, 23, 59, 53, 1], "R": 15844}, {"C": [63, 57, 60, 54, 0], "R": 15844}, {"C": [64, 58, 61, 36], "R": 16356}, {"C": [65, 59, 62, 55, 1], "R": 15844}, {"C": [66, 60, 63, 13, 0], "R": 15844}, {"C": [67, 61, 64, 56], "R": 16356}, {"C": [68, 62, 65, 57], "R": 16356}, {"C": [69, 63, 66, 58], "R": 16356}, {"C": [70, 21, 67, 59], "R": 16356}, {"C": [71, 64, 68, 60], "R": 16356}, {"C": [72, 65, 69, 40], "R": 16356}, {"C": [73, 66, 70, 61], "R": 16356}, {"C": [74, 67, 71, 36], "R": 16356}, {"C": [75, 68, 72, 62, 0, 2], "R": 15812}, {"C": [76, 69, 1, 73, 45, 0], "R": 15840}, {"C": [77, 70, 0, 74, 63, 1], "R": 15840}, {"C": [78, 71, 75, 64, 0], "R": 15844}, {"C": [79, 1, 76, 65], "R": 16356}, {"C": [80, 72, 77, 66, 1], "R": 15844}, {"C": [81, 50, 78, 67], "R": 16356}, {"C": [82, 73, 79, 68, 0], "R": 15844}, {"C": [83, 41, 80, 69], "R": 16356}, {"C": [84, 74, 81, 26], "R": 16356}, {"C": [85, 75, 82, 70], "R": 16356}, {"C": [86, 76, 83, 71], "R": 16356}, {"C": [87, 12, 84, 72], "R": 16356}, {"C": [88, 77, 85, 73], "R": 16356}, {"C": [89, 32, 86, 74], "R": 16356}, {"C": [90, 78, 87, 38], "R": 16356}, {"C": [91, 79, 88, 13, 1], "R": 15844}, {"C": [92, 80, 89, 75, 0], "R": 15844}, {"C": [93, 1, 90, 76, 2], "R": 15844}, {"C": [94, 81, 91, 77, 1], "R": 15844}, {"C": [95, 82, 92, 27, 0], "R": 15844}, {"C": [96, 83, 93, 40, 5, 1, 1, 1], "R": 3780}, {"C": [97, 84, 94, 78], "R": 16356}, {"C": [98, 85, 95, 79], "R": 16356}, {"C": [99, 86, 96, 80], "R": 16356}, {"C": ["R190810097337", 87, 97, 81, 2, 2], "R": 12004}, {"C": ["R190810097336", 88, 98, 82, 3, 3], "R": 12004}, {"C": ["R190810097335", 89, 99, 45], "R": 16356}, {"C": ["R190810097334", 90, "RAJESH RAM", 83], "R": 16356}, {"C": ["R190810097333", 91, "RAJKAPUR SAW", 84], "R": 16356}, {"C": ["R190810097332", 13, "ARUN MAHTO", 73], "R": 16356}, {"C": ["R190810097331", 51, "ANIL PASWAN", 85, 1], "R": 15844}, {"C": ["R190810097330", 92, "VINOD KUMAR", 35], "R": 16356}, {"C": ["R190810097329", 93], "R": 16380}, {"C": ["R190810097328", 94, "AJIT KUMAR", 68], "R": 16356}, {"C": ["R190810097327", "HARINANDAN PASWAN", 86], "R": 16358}, {"C": ["R190810097326", 71, "RAMESHWAR PASWAN", 87], "R": 16356}, {"C": ["R190810097325", 95, "KISHOR PASWAN", 88], "R": 16356}, {"C": ["R190810097324", 96, "SUNIL KUMAR", 45, 0], "R": 15844}, {"C": ["R190810097323", 1, "DHARMENDRA KEWAT", 5], "R": 16356}, {"C": ["R190810097322", 97, "GANESH MISTRI", 89], "R": 16356}, {"C": ["R190810097321", 98, "AMRIT PASWAN", 18, 1], "R": 15844}, {"C": ["R190810097320", 99, "BHUSHAN MISTRI", 40, 0], "R": 15844}, {"C": ["R190810097319", "DINANATH KUMAR", "BACHCHU DAS", 21], "R": 16356}, {"C": ["R190810097318", "RAKESH KUMAR", "AJAY KUMAR", 90], "R": 16356}, {"C": ["R190810097317", "NIRAJ KUMAR", "NARESH PRASAD", 7], "R": 16356}, {"C": ["R190810097316", "GANESH KUMAR", "SHIYA SHARAN RAVIDAS", 91, 1], "R": 15844}, {"C": ["R190810097315", "DEEPAK KUMAR", "KAMESHWAR RAVIDAS", 31], "R": 16356}, {"C": ["R190810097314", "SANJAY PANDIT", "NARAYAN PANDIT", 92, 0], "R": 15844}, {"C": ["R190810097313", "MANTU KUMAR", "RAMASHRAY RAVIDAS", 93, 1], "R": 15844}, {"C": ["R190810097312", "MANISH KUMAR", "JAGLAL CHAUDHARY", 94], "R": 16356}, {"C": ["R190810097311", "SATENDRA CHAUDHARY", "KRISHN CHAUDHARY", 56], "R": 16356}, {"C": ["R190810097310", 98, "RAMISVAR RAVIDASH", 38], "R": 16356}, {"C": ["R190810097309", "AKASH KUMAR", "ASHOK THAKUR", 69, 0], "R": 15844}, {"C": ["R190810097308", "MANOJ KR MALLAH", "GAYA MALLAH", 95], "R": 16356}, {"C": ["R190810097307", "MANTU KUMAR", "SHAMBHU PRASAD", 11], "R": 16356}, {"C": ["R190810097306", 1, "BABLU KUMAR", 96, 2], "R": 15844}, {"C": ["R190810097305", "MOHIT KUMAR", "RAJ KUMAR RAJAK", 73, 1], "R": 15844}, {"C": ["R190810097304", "AMITESH KUMAR", "SIKANDRA SINGH", 97, 2], "R": 15844}, {"C": ["R190810097303", "MD MERAJ", "MD REYAJ", 98, 0], "R": 15844}, {"C": ["R190810097302", "RITESH KUMAR RAUSHAN", "MUKESH NIRALA", 99], "R": 16356}, {"C": ["R190810097301", 62, "KUMOD YADAV", "JAYA DEVI"], "R": 16356}, {"C": ["R190810097300", "RAVISHANKAR KUMAR", "NARAYAN SINGH", 68, 2], "R": 15844}, {"C": ["R190810097299", "SHUBHAM RAJ", "SHANKAR KUMAR", 46], "R": 16356}, {"C": ["R190810097298", "KM POOJA KUMARI GOND", 1, "SATYENDRA GOND", "VINDU DEVI", 3], "R": 15840}, {"C": ["R190810097297", "NEHA KUMARI", "VINAY KUMAR SAH", 73, 6, 4, 0, 4, 0], "R": 3268}, {"C": ["R190810097296", "UDAY BHARTI", 0, "BALRAM PARSAD", 5, 2, 2, 1], "R": 3792}, {"C": ["R190810097295", "NIRAJ KUMAR", "CHANDRIKA PANDIT", "DHANO DEVI"], "R": 16356}, {"C": ["R190810097294", "UTTAM KUMAR", "CHANASWAR PRASAD", 12], "R": 16356}, {"C": ["R190810097293", 65, "MANNU THAKUR", "GIRJA DEVI"], "R": 16356}, {"C": ["R190810097292", "OMPRAKASH KUMAR", "GOVIND SHARMA", 1], "R": 16356}, {"C": ["R190810097291", 64, "PRAMOD YADAV", 94], "R": 16356}, {"C": ["R190810097290", "JAYDEV KUMAR", "KRISHNA PRASAD", "KRISHNA SHAHI"], "R": 16356}, {"C": ["R190810097289", "AATISH KUMAR", "SUDHIR SINGH", 49], "R": 16356}, {"C": ["R190810097288", "BALRAM KUMAR", "NAGENDRA KUMAR", "MALTI DEVI"], "R": 16356}, {"C": ["R190810097287", "RAJA KUMAR", "BHOLA PRASAD", "ANSHU DEVI"], "R": 16356}, {"C": ["R190810097286", 94, "SURESH PRASAD", 21], "R": 16356}, {"C": ["R190810097285", "ARVIND KUMAR", "SANJAY PRASAD", 33], "R": 16356}, {"C": ["R190810097284", "RAJENDRA CHAUHAN", "SUDHA DEVI"], "R": 16358}, {"C": ["R190810097283", "DHARMVIR KUMAR", "AJAY PANDIT", "KALAWATI DEVI"], "R": 16356}, {"C": ["R190810097282", "Vikram kumar", "CHANDRA BHUSHAN", "BABITA DEVI", 2], "R": 15844}, {"C": ["R190810097281", "AMAN RAJ", "RAJESH PRASAD", 0], "R": 15860}, {"C": ["R190810097280", 37, "RAMASHISH BHUIYAN", 15, 1], "R": 15844}, {"C": ["R190810097279", "KOMAL KUMARI", 1, "RAJEEV KUMAR SINGH", 90, 2], "R": 15840}, {"C": ["R190810097278", "BARUN PASWAN", 0, "AVADHESH PASWAN", 31, 1], "R": 15840}, {"C": ["R190810097277", "DEEPAK KUMAR", "BHONDU MANJHI", "SUKARI DEVI"], "R": 16356}, {"C": ["R190810097276", "ANOJ RAVIDAS", "RAJKUMAR RAVIDAS", "KUNTI DEVI"], "R": 16356}, {"C": ["R190810097275", "KARAN KUMAR", "NARESH RAVIDAS", 5], "R": 16356}, {"C": ["R190810097274", "ANKIT KUMAR", "SANTOSH RAVIDAS", "SAKUNTALA DEVI"], "R": 16356}, {"C": ["R190810097273", "JITENDRA KUMAR", "MANOJ RAUT", "NEELAM DEVI", 0], "R": 15844}, {"C": ["R190810097272", 98, "VINOD SINGH", "NUTAN DEVI", 2], "R": 15844}, {"C": ["R190810097271", "ANSHUMAN KUMAR", "MANOJ KUMAR", "ANAMIKA KUMARI"], "R": 16356}, {"C": ["R190810097270", "MANISH KUMAR", "RAMDAHIN SINGH", "RANJAN DEVI"], "R": 16356}, {"C": ["R190810097269", "MUNCHUN KUMAR", "VISHESHWAR RAVIDAS", "DHANISHWARI DEVI", 1], "R": 15844}, {"C": ["R190810097268", "MONU KUMAR", "PRAMOD SINGH", "MIGURLA DEVI", 2], "R": 15844}, {"C": ["R190810097267", "ARTI KUMARI", 1, "PINTU SINGH", "SHRMILA DEVI"], "R": 16352}, {"C": ["R190810097266", "SAURAV KUMAR", 0, "PRAVIN KUMAR", 31], "R": 16352}, {"C": ["R190810097265", 37, "Kapildeo singh", 74], "R": 16356}, {"C": ["R190810097264", "AMIT KUMAR", "VEDPRAKASH", "BOBY DEVI"], "R": 16356}, {"C": ["R190810097263", 51, "SANJIV KUMAR", 97, 0], "R": 15844}, {"C": ["R190810097262", 9, "RAJENDRA CHOUDHARY", "RANI DEVI", 1], "R": 15844}, {"C": ["R190810097261", 35], "R": 16380}, {"C": ["R190810097260", "GOPAL KUMAR", "NEWTON SINGH", "BIBHA DEVI", 2], "R": 15844}, {"C": ["R190810097259", 23, "RAM CHNDRA SINGH", 49], "R": 16356}, {"C": ["R190810097258", "RANI KUMARI", 1, "AJAY PASWAN", "GEETA DEVI", 1], "R": 15840}, {"C": ["R190810097257", "RAUNAK RAJ", 0, "MITHLESH KUMAR", "SWARNLATA DEVI", 0, 0], "R": 15808}, {"C": ["R190810097256", "SAURAV VERMA", "SHANKAR PRASAD VERMA", 73], "R": 16356}, {"C": ["R190810097255", 83, "SHYAM SUNDER PRASAD", 15], "R": 16356}, {"C": ["R190810097254", 23, "RAJENDRA PRASAD", "CHAMELI DEVI"], "R": 16356}, {"C": ["R190810097253", "SINTU PRASAD", "SOME PRAKASH PRASAD", 94], "R": 16356}, {"C": ["R190810097252", "SHIVAM KUMAR", "CHHOTE LAL PRASAD", 54], "R": 16356}, {"C": ["R190810097251", "RAJ KUMAR", "MATHURA PRASAD", "RAM DYARI DEVI"], "R": 16356}, {"C": ["R190810097250", "RAVIRANJAN KUMAR", "BIHARI PRASAD", "SIYA DEVI"], "R": 16356}, {"C": ["R190810097249", "AVINASH KUMAR", "BINDU MAHTO", 69], "R": 16356}, {"C": ["R190810097248", 56, "SHYAM SUNDAR PD VERMA", "ASHA DEVI"], "R": 16356}, {"C": ["R190810097247", 63, "VIJAY PRASAD", 12], "R": 16356}, {"C": ["R190810097246", "ANJU KUMARI", 1, "MISHRI YADAV", 40], "R": 16352}, {"C": ["R190810097245", "AMAN PRASAD", 0, "BALESHWAR PRASAD", "NILKAMAL DEVI"], "R": 16352}, {"C": ["R190810097244", "AMIT KUMAR", "SHIV SHANKAR PRASAD", 90], "R": 16356}, {"C": ["R190810097243", "PRINCE RAJ", "PRAMOD KUMAR", "KUMARI BEENA"], "R": 16356}, {"C": ["R190810097242", "MD RIZWAN ALAM", "MD IMTIYAZ AHMAD", "SULTANA PERWEEN"], "R": 16356}, {"C": ["R190810097241", 56, "SHAMBHU PRASAD", 47], "R": 16356}, {"C": ["R190810097240", "AKASH KUMAR", "BINOD PRASAD", 46], "R": 16356}, {"C": ["R190810097239", "ANSHU KUMAR", "Alok Prasad", 18], "R": 16356}, {"C": ["R190810097238", "NITISH KUMAR", "NAVAL RAM", 15], "R": 16356}, {"C": ["R190810097237", "MANISH KUMAR", "ASHOK SAW", 12], "R": 16356}, {"C": ["R190810097236", "SATYA KUMARI", 1, "ARJUN PRASAD GUPTA", "SANGEETA DEVI"], "R": 16352}, {"C": ["R190810097235", "SHWET NISHA", "VINOD KUMAR", "KIRAN KUMARI"], "R": 16356}, {"C": ["R190810097234", "TRIDEV KUMAR", 0, "BHIM PRASAD YADAV", 74], "R": 16352}, {"C": ["R190810097233", 83, "AJAY PRASAD", 18], "R": 16356}, {"C": ["R190810097232", 21, "RAJENDRA MAHTO", "SHAILA KUMARI"], "R": 16356}, {"C": ["R190810097231", "SANTU KUMAR", "SURESH CHOUDHARY", "KOSHALYA DEVI", 1], "R": 15844}, {"C": ["R190810097230", "GULSHAN KUMAR", "RAVINDRA SINGH", "AHILYA DEVI", 2], "R": 15844}, {"C": ["R190810097229", 90, "ARUN SINGH", "REENA DEVI"], "R": 16356}, {"C": ["R190810097228", "NAMAN KUMAR", "CHITRANJAN KUMAR", "RUNI KUMARI"], "R": 16356}, {"C": ["R190810097227", 48, "GORELAL SINGH", "Rubi Devi"], "R": 16356}, {"C": ["R190810097226", 21, "LAL BABU", "BABY KUMARI"], "R": 16356}, {"C": ["R190810097225", 1, "GAUTAM NONIYA", "VIDYA DEVI", 0], "R": 15844}, {"C": ["R190810097224", "RAJNISH KUMAR", "ASHOK SINGH", 97, 2], "R": 15844}, {"C": ["R190810097223", "KANHAIYA JI", "SURENDRA KUMAR", "BINA KUMARI"], "R": 16356}, {"C": ["R190810097222", "GANESH KUMAR", "SITARAM MAHTO", "SUMITRA DEVI", 0], "R": 15844}, {"C": ["R190810097221", 23, "PAPPU SINGH", "BOBI DEVI", 2], "R": 15844}, {"C": ["R190810097220", "JYOTI KUMARI", 1, "SANJAY KUMAR", "MANJU KUMARI"], "R": 16352}, {"C": ["R190810097219", "AMIT KUMAR", 0, "SHIV SHANKAR SINGH", "MANI DEVI"], "R": 16352}, {"C": ["R190810097218", "MOHIT KUMAR", "SATENDRA KUMAR", 56], "R": 16356}, {"C": ["R190810097217", "CHHOTU KUMAR", "KAILASH CHOUDHARY", "BINDU DEVI", 5, 5], "R": 12004}, {"C": ["R190810097216", "NEEL KAMAL", "KUMOD CHANDRA MISHRA", "MAMTA DEVI", 5], "R": 16324}, {"C": ["R190810097215", 7, "RAMDEV PASWAN", "BASMATI DEVI", 1], "R": 15844}, {"C": ["R190810097214", "JOHN RAJ", "BIPIN KUMAR", "PREMLATA KUMARI", 0], "R": 15844}, {"C": ["R190810097213", 98, "SUNIL MANDAL", 63], "R": 16356}, {"C": ["R190810097212", "SATYAM KUMAR", "UPENDRA KUMAR VISHWASI", "BISHEKHA DEVI"], "R": 16356}, {"C": ["R190810097211", "MD RAJA", "MD MUMTAJ AHMAD", "FARHAT ARA"], "R": 16356}, {"C": ["R190810097210", "SHASHI KUMAR", "ARJUN PANDIT", "BIMLA DEVI"], "R": 16356}, {"C": ["R190810097209", "ANIL KUMAR", "JANARDHAN PRASAD", "SONAJHARI DEVI", 7, 1, 6, 6], "R": 11908}, {"C": ["R190810097208", "SURAJ KUMAR", "SHANKAR PRASAD", "LALTI DEVI", 0, 0, 7], "R": 12164}, {"C": ["R190810097207", "PARTHA SARKAR", "NISHIKANTA SARKAR", "LALITA SARKAR", 5, 1], "R": 15812}, {"C": ["R190810097206", "ANKIT KUMAR", "OM PRAKASH PANDIT", "RAMA KUMARI", 1, 0, 1], "R": 11492}, {"C": ["R190810097205", "AKASH CHAUDHARY", "VINOD CHAUDHARY", "SOBHA DEVI", 0], "R": 16324}, {"C": ["R190810097204", "NAKUL PASWAN", "SUNIL PASWAN", 69, 1], "R": 15844}, {"C": ["R190810097203", "SANJAY KUMAR", "NEPALI YADAV", "SHOHAGI DEVI", 0], "R": 15844}, {"C": ["R190810097202", "SHIVLOK KUMAR", "BALDEV PANDIT", "RITU DEVI"], "R": 16356}, {"C": ["R190810097201", "SAURAV KUMAR", "TANIKAN RAM", "ANJU DEVI"], "R": 16356}, {"C": ["R190810097200", "UDAY PRASAD", "MADHESH MAHTO", "RAMKALI DEVI"], "R": 16356}, {"C": ["R190810097199", "ANKIT RAJ", "HIRA LAL CHOUDHARY", 96], "R": 16356}, {"C": ["R190810097198", "SHIVAM KUMAR", "SHAILENDRA CHAUDHARY", 89], "R": 16356}, {"C": ["R190810097197", 58, "RAMNATH PANDIT", 5, 2, 1, 7, 0, 0], "R": 3716}, {"C": ["R190810097196", 89, "SURESH PASWAN", "SITLI DEVI", 5, 0, 1], "R": 15748}, {"C": ["R190810097195", "SUKOMAL DAS", "SUBHASH CHANDRA DAS", "RANI DEVI", 0, 8, 0, 8], "R": 11460}, {"C": ["R190810097194", "DIVYANSHU KUMAR", "AJAY KUMAR", "VIBHA SINHA", 2], "R": 15844}, {"C": ["R190810097193", "MASUM ALI", "MD KAMRUL HODA", "NASIMA KHATOON", 0], "R": 15844}, {"C": ["R190810097192", "AZIT KUMAR PANDEY", "PANCHANAND PANDEY", "MALTI DEVI", 2], "R": 15844}, {"C": ["R190810097191", "REETIK RAUSHAN KUMAR", "RAJESH SINGH", 54], "R": 16356}, {"C": ["R190810097190", "ANAND KUMAR", "RAVINDRA KUMAR PATHAK", 31], "R": 16356}, {"C": ["R190810097189", 80, "CHANDESHWAR PRASAD", "PRAMILA DEVI", 0], "R": 15844}, {"C": ["R190810097188", 76, "DHUPLAL MAHTO", "SHARADA DEVI"], "R": 16356}, {"C": ["R190810097187", 71, "JAYANANAD RAY", "RAMUNI DEVI"], "R": 16356}, {"C": ["R190810097186", "SHWETA KUMARI", 1, "LAKHRAJ SAH", "SIYA DEVI"], "R": 16352}, {"C": ["R190810097185", "BEDPRAKASH KUMAR", 0, "RAM AYODHYA PRASAD YADAV", "GUJAWANTI DEVI"], "R": 16352}, {"C": ["R190810097184", "MANTU KUMAR PANDIT", "SHIVANANDAN PANDIT", "KRISHANAVATI DEVI"], "R": 16356}, {"C": ["R190810097183", "SHATRUDHAN KUMAR KUSHWAHA", "BADRI PRASAD KUSHWAHA", 23], "R": 16356}, {"C": ["R190810097182", "SACHIN KUMAR RAI", "VINOD KUMAR RAI", "NEELAM DEVI", 9, 2, 9, 1], "R": 3300}, {"C": ["R190810097181", "MANU KUMAR RAI", "RAMJI RAI", "CANDRAWATI DEVI"], "R": 16356}, {"C": ["R190810097180", 51, "JAYPRAKASH PASWAN", 23, 1], "R": 15844}, {"C": ["R190810097179", "SATYAM KUMAR CHAUBEY", "ROHIT NANDAN CHAUBEY", "ANJU CHAUBEY", 2], "R": 15844}, {"C": ["R190810097178", "VINDHYACHAL PAL", "MAHENDAR PAL", "KALAVATI DEVI", 0], "R": 15844}, {"C": ["R190810097177", "GAUTAM SINGH KUSHWAHA", "DEVMUNI KUSHWAHA", "SAVITA KUSHWAHA"], "R": 16356}, {"C": ["R190810097176", 94, "DAROGA SINGH", "GIRAJA DEVI"], "R": 16356}, {"C": ["R190810097175", "NIRAJ SINGH", "BINDESHWARI SINGH", "PRAVINDA DEVI"], "R": 16356}, {"C": ["R190810097174", "DHIRAJ KUMAR SINGH", "BIRENDRA  PRASAD SINGH", 11], "R": 16356}, {"C": ["R190810097173", "Manish Kumar singh", "MANOJ KUMAR SINGH", "INDU DEVI"], "R": 16356}, {"C": ["R190810097172", "LALU PRASAD", "MAHENDRA SINGH", "MANTA DEVI"], "R": 16356}, {"C": ["R190810097171", "NITU KUMARI", 1, "SUDARSHAN PRAJAPATI", "PRAMILA DEVI"], "R": 16352}, {"C": ["R190810097170", "UPENDRA KUMAR YADAV", 0, 6, "KAMLESHEE DEVI"], "R": 16352}, {"C": ["R190810097169", "DEEPAK KUMAR GOSWAMI", "AJAY GOSWAMI", "PUSHPA DEVI"], "R": 16356}, {"C": ["R190810097168", "LAL BABU SAH", "SHRI GANESH SAH", "BACHMUNA DEVI"], "R": 16356}, {"C": ["R190810097167", "NIRANJAN SINGH", "BHOLA NATH SINGH", "JANKI DEVI"], "R": 16356}, {"C": ["R190810097166", "PIYUSH KUMAR", "SANJAY KUMAR SINGH", "RAMBHA DEVI", 2], "R": 15844}, {"C": ["R190810097165", "MUNNA PASWAN", "PHOOLESHWAR PASWAN", "GULABO DEVI", 5, 10, 1, 10], "R": 11460}, {"C": ["R190810097164", "DABLU KUMAR", "AKHILESH SINGH", "ASHA DEVI", 0, 3, 2, 11], "R": 11460}, {"C": ["R190810097163", 98, "SIGASAN YADAV", 23, 5, 0], "R": 15812}, {"C": ["R190810097162", "RUPAM KUMAR", "SHIV SHANKAR PRASAD", "KUMARI ARCHANA", 0], "R": 16324}, {"C": ["R190810097161", 89, "BIJAY RAY", "CHANDRAWATI DEVI"], "R": 16356}, {"C": ["R190810097160", "ANAND MOHAN"], "R": 16380}, {"C": ["R190810097159", "SHREYA KUMARI", 1, "SHIV SHANKAR PRASAD", "KUMARI ARCHANA"], "R": 16352}, {"C": ["R190810097158", "MD IRFAN ALAM", 0, "MD ANWAR ALAM", "ROSHAN KHATUN"], "R": 16352}, {"C": ["R190810097157", 28, "LALBAHADUR PRASAD", "PHULMANTI DEVI", 5], "R": 16324}, {"C": ["R190810097156", 30, "MOHAN PRASAD GUPTA", "KALAWATI DEVI"], "R": 16356}, {"C": ["R190810097155", "IRFAN ANSARI", "SERAJUDDIN ANSARI", "NOORUN NESHA", 8, 8, 8, 0], "R": 3780}, {"C": ["R190810097154", "SUMANT KUMAR", "RAJKISHOR THAKUR", "MITA DEVI"], "R": 16356}, {"C": ["R190810097153", "CHUNNU KUMAR", 4, 54], "R": 16356}, {"C": ["R190810097152", "MD. SHAMIM", "ASHMOHAMMAD ANSARI", "NOOR NESHA"], "R": 16356}, {"C": ["R190810097151", "AMIT KUMAR", "SANJAY KUMAR SHARMA", 23, 5], "R": 16324}, {"C": ["R190810097150", 30, "RAJENDRA HAZRA", "KRISHNAWATI DEVI", 1], "R": 15844}, {"C": ["R190810097149", 21, "LAXSHMAN PRASAD", "INDU DEVI", 0], "R": 15844}, {"C": ["R190810097148", "SIKEENDRA KUMAR RAY", "BHUNESHWAR RAY", "RAMBHA DEVI"], "R": 16356}, {"C": ["R190810097147", 56, "NANDLAL PRASAD", 67], "R": 16356}, {"C": ["R190810097146", "SIPAHI KUMAR", "DHANRAJ YADAW", "SUGANTI DEVI"], "R": 16356}, {"C": ["R190810097145", "ALOK KUMAR", "VEER NARAYAN KUNWAR", "SOSHEELA DEVI", 2], "R": 15844}, {"C": ["R190810097144", "KANCHAN KUMAR", "BRAHMA PRASAD", 31, 0], "R": 15844}, {"C": ["R190810097143", "MEGHNATH KUMAR PATEL", "RAMESHWAR PATEL", "SUGANDHI DEVI"], "R": 16356}, {"C": ["R190810097142", "AWADHESH KUMAR", "RAJENDRA SHARMA", "SARSWATI DEVI", 3], "R": 15844}, {"C": ["R190810097141", "ARUN KUMAR GIRI", "RAM KISHOR GIRI", "SHILA KUNWAR", 0], "R": 15844}, {"C": ["R190810097140", 51, "SUNIL KUMAR", 38, 2], "R": 15844}, {"C": ["R190810097139", "UDAY NARAYAN PRASAD", "DWARIKA PRASAD", 45, 0], "R": 15844}, {"C": ["R190810097138", "MOHIT KUMAR", "RATAN KUMAR SARAF", "PRATIMA DEVI"], "R": 16356}, {"C": ["R190810097137", "SAROJ KUMAR YADAV", "SHAMBHU PRASAD YADAV", "MALTEE DEVI"], "R": 16356}, {"C": ["R190810097136", "AKHILESH KUMAR", "MERO LAL RAY", "SONAWA DEVI"], "R": 16356}, {"C": ["R190810097135", "AMIT KUSHWAHA", 63, "BHAGWANTI DEVI"], "R": 16356}, {"C": ["R190810097134", 51, "MANOJ PRASAD GUPTA", "VEENA GUPTA"], "R": 16356}, {"C": ["R190810097133", "RIKESH KUMAR", "NAWAL KISHOR SINGH", "INDU DEVI"], "R": 16356}, {"C": ["R190810097132", "RANJEET KUMAR RANJAN", "BACHA PRASAD", "RAMPRABHA DEVI"], "R": 16356}, {"C": ["R190810097131", "RAKESH KUMAR", "RAM JANM BHAGAT", 61], "R": 16356}, {"C": ["R190810097130", 51, "GIRISHDEV RAI", "KALAWATI DEVI"], "R": 16356}, {"C": ["R190810097129", 94, "RAVINDRA KUMAR PRASAD", 73], "R": 16356}, {"C": ["R190810097128", "PRADEEP KUMAR", "SHIVJEE SAH", "RAJVANTI DEVI"], "R": 16356}, {"C": ["R190810097127", 76, "BAIJU SAH", "MUNDIRKA DEVI"], "R": 16356}, {"C": ["R190810097126", "CHHOTELAL SAH", "HAJARI SAH", "RAMA DEVI"], "R": 16356}, {"C": ["R190810097125", "MANISH KUMAR", "JIYALAL PRASAD", "DHANMANTI DEVI"], "R": 16356}, {"C": ["R190810097124", "PRATIK KUMAR MISHRA", "JITENDRA MISHRA", "SANGEETA MISHRA", 2], "R": 15844}, {"C": ["R190810097123", "RAKESH KUMAR", "RAVINDRA PRASAD", "GAURAPATI DEVI", 0], "R": 15844}, {"C": ["R190810097122", "NAYAN THAKUR", "SARSWATI DEVI", 3], "R": 15846}, {"C": ["R190810097121", "DHARMESH KUMAR RAM", "DHRUW RAM", "UMA DEVI", 1], "R": 15844}, {"C": ["R190810097120", "PANKAJ KUMAR", "RAMASHISH SAH", "GEETA DEVI", 0], "R": 15844}, {"C": ["R190810097119", "ABID ANSARI", "MAULADIN ANSARI", "SABRUN NESA"], "R": 16356}, {"C": ["R190810097118", 31, "UPENDRA PRASAD GUPTA", 31], "R": 16356}, {"C": ["R190810097117", "BHAGESHWAR KUMAR", "ASHARFI SAHANI", "SHANTI DEVI"], "R": 16356}, {"C": ["R190810097116", "IRSHAD ALAM", "MOBARAK HUSSIAN", "MAIMUN NESHA"], "R": 16356}, {"C": ["R190810097115", "ABID ALAM", "MOHAMMAD SALIM ANSARI", "ZAIBUN NESHA"], "R": 16356}, {"C": ["R190810097114", "AKASH KUMAR", "RAJESH PRASAD", "KUNTI DEVI"], "R": 16356}, {"C": ["R190810097113", 89, "DINESH SAH", "ANITA GUPTA"], "R": 16356}, {"C": ["R190810097112", "INDRAJIT KUMAR", "BIRBAL PASWAN", "KALAWATI DEVI", 3, 1, 11, 1], "R": 3300}, {"C": ["R190810097111", "SOHIT KUMAR", "GANDHI PRASAD", "PRAMILA DEVI", 0], "R": 15844}, {"C": ["R190810097110", "NITESH KUMAR", "BIRENDRA SAW", "SABITA DEVI"], "R": 16356}, {"C": ["R190810097109", 96, "ANORATH VERMA", "SONAJHRI DEVI"], "R": 16356}, {"C": ["R190810097108", "VISHAL PATEL", "BIJENDRA SINGH", "PRAMILA DEVI"], "R": 16356}, {"C": ["R190810097107", 89, "RAJNATH YADAV", 89], "R": 16356}, {"C": ["R190810097106", "DHIRAJ KUMAR", "LAXMAN SAW", "JANKI DEVI"], "R": 16356}, {"C": ["R190810097105", "Ravi Shankar Kumar", "NARESH RAM", "PUNAM DEVI"], "R": 16356}, {"C": ["R190810097104", "DHRUB KUMAR", "RAJESH PRASAD", "KAMLAVATI DEVI"], "R": 16356}, {"C": ["R190810097103", "AMARKANT VERMA", "RAMSIHASAN SINGH", 23], "R": 16356}, {"C": ["R190810097102", "SUBHASH KUMAR", "SURESH BAITHA", "SARSWATI DEVI", 0, 8, 1, 8, 0], "R": 3268}, {"C": ["R190810097101", "SANJEEV RANJAN", "RAJKISHOR PASWAN", "NEELAM DEVI"], "R": 16356}, {"C": ["R190810097100", "PAPPU RAM", "BABU RAM", 68], "R": 16356}, {"C": ["R190810097099", "RAJEEV RANJAN", "RAJ KISHOR PASWAN", "NEELAM DEVI"], "R": 16356}, {"C": ["R190810097098", 23, "JAYKISHAN RAM", "KAUSHALAYA DEVI"], "R": 16356}, {"C": ["R190810097097", 10, "KULDIP SAHANI", "SHANTI DEVI", 0], "R": 15844}, {"C": ["R190810097096", 30, "NARSINGH SHARMA", "PRABHAWATI DEVI", 3], "R": 15844}, {"C": ["R190810097095", "DEEPAK KUMAR", "YADAVLAL MAHTO", "BACHIYA DEVI", 0], "R": 15844}, {"C": ["R190810097094", 95, "SHIV SHANKAR PRASAD", "MAMTA DEVI"], "R": 16356}, {"C": ["R190810097093", "RAVISHANKAR KUMAR", "KAMESHWAR SINGH", "SIMA DEVI", 2], "R": 15844}, {"C": ["R190810097092", "AKASH KUMAR", "MANTU SINGH", "REENA DEVI", 5, 3, 11, 1], "R": 3780}, {"C": ["R190810097091", "vivek raj", "NITYANAND SINGH", 56], "R": 16356}, {"C": ["R190810097090", "RANJAN KUMAR", "RAVINDRA CHAUDHARY", "SAKUNTLA DEVI", 0], "R": 15844}, {"C": ["R190810097089", "PRAVIND KUMAR", "BIRENDRA PRASAD", "TILESHWARI DEVI", 1], "R": 15844}, {"C": ["R190810097088", 12, "RAM NARYAN RAM", "MANMATIYA DEVI"], "R": 16356}, {"C": ["R190810097087", "KAILASH KUMAR", "SANJAY YADAV", "CHANDRAWATI DEVI", 0], "R": 15844}, {"C": ["R190810097086", "SURYA KUMAR", "DEVANAND VISHWAKARMA", "RADHA DEVI"], "R": 16356}, {"C": ["R190810097085", 98, "HARENDRA RAY", "FULKESHRI DEVI"], "R": 16356}, {"C": ["R190810097084", "RAJ KUMAR", "UDAY PRASAD SINGH", "GUMTA DEVI"], "R": 16356}, {"C": ["R190810097083", "AMIT KUMAR", "SUGAN SAW", 73], "R": 16356}, {"C": ["R190810097082", "NANDAN KUMAR", "SANTU DAS", "SHANTI DEVI", 3, 8, 1, 8, 0], "R": 3268}, {"C": ["R190810097081", "NIRANJAN KUMAR", "HRIDESH BHAGAT", "PREMSHEELA DEVI", 0], "R": 15844}, {"C": ["R190810097080", "RANJEET KUMAR", "RAJDEV PRASAD", 13], "R": 16356}, {"C": ["R190810097079", "SHIVAM KUMAR", "SONALAL RAM", "SHILA  DEVI", 1], "R": 15844}, {"C": ["R190810097078", "BHOLA KUMAR", "JITENDRA RAM", 43], "R": 16356}, {"C": ["R190810097077", "AJAY KUMAR DAS", "SUKHADI DAS", "RABADI DEVI"], "R": 16356}, {"C": ["R190810097076", "Sonu Raj", "SURESH PRASAD YADAV", "PRAMILA DEVI", 0], "R": 15844}, {"C": ["R190810097075", "SONALAL KUMAR", "NANDLAL PRASAD YADAV", "RAJKALI DEVI", 2], "R": 15844}, {"C": ["R190810097074", "NAVNIT KUMAR", "RAJENDRA RAY", 31, 0], "R": 15844}, {"C": ["R190810097073", "PRAMOD KUMAR", "NAGESHWAR RAY", "SONA DEVI"], "R": 16356}, {"C": ["R190810097072", "UTTAM KUMAR", "KUMOD PATEL", "REEMA DEVI"], "R": 16356}, {"C": ["R190810097071", "APURV RAJ", "HARISHANKAR PRASAD", 68, 2], "R": 15844}, {"C": ["R190810097070", 94, "JAGYA THAKUR", 36, 0], "R": 15844}, {"C": ["R190810097069", "SUSHIL KUMAR", "KRISHNA VERMA", "KAMNI DEVI", 5, 3, 11, 1], "R": 3780}, {"C": ["R190810097068", 90, "RAMLAYAK YADAV", "PACHRATAN DEVI"], "R": 16356}, {"C": ["R190810097067", "Subodh Kumar", "MAHESH KUMAR RAY", "SAMPATO DEVI"], "R": 16356}, {"C": ["R190810097066", "RAJ KUMAR", "MITHILESH BHAGAT", "KARUNA DEVI"], "R": 16356}, {"C": ["R190810097065", "DEEPAK KUMAR RAY", "LALAN RAY", "MUNNI DEVI"], "R": 16356}, {"C": ["R190810097064", "GUDDU KUMAR", "RAM BABU RAI", "LAILUN DEVI"], "R": 16356}, {"C": ["R190810097063", "RAVINDRA KUMAR", "UMESH SINGH", "KRISHNA DEVI"], "R": 16356}, {"C": ["R190810097062", "AMAN VERMA", "DEO KANT VERMA", 94], "R": 16356}, {"C": ["R190810097061", "RAVI RANJAN PAL", "RAJENDRA PAL", "CHANDRAVATI DEVI"], "R": 16356}, {"C": ["R190810097060", "RISHU KUMAR", "MADAN KUMAR", "PUSHPA DEVI"], "R": 16356}, {"C": ["R190810097059", "MUKESH KUMAR MISHRA", "AMAR NATH MISHRA", 13, 9, 8, 2, 8, 0], "R": 3268}, {"C": ["R190810097058", 22, "RAJU PRASAD YADAV", "AMIRA DEVI", 0], "R": 15844}, {"C": ["R190810097057", "RAGHVENDRA KUMAR YADAV", "SHAMBHU PRASAD YADAV", "BACCHI DEVI"], "R": 16356}, {"C": ["R190810097056", 21, "SUNIL KUMAR PANDEY", "MALA PANDEY", 2], "R": 15844}, {"C": ["R190810097055", 98, "BABULAL YADAV", 43, 0], "R": 15844}, {"C": ["R190810097054", "PRABHAKAR KUMAR", "ASHOK KUMAR", "PRITI DEVI"], "R": 16356}, {"C": ["R190810097053", "KRISHNA KUMAR", "YOGENDRA PRASAD YADAV", "JALESHWARI DEVI"], "R": 16356}, {"C": ["R190810097052", "BALRAM KUMAR", "JAGU PRASAD YADAV", "BALSHREE DEVI"], "R": 16356}, {"C": ["R190810097051", "SHSHI KUMAR", "VIJAY SINGH", "MANORMA DEVI", 5, 3, 2, 11, 1], "R": 3268}, {"C": ["R190810097050", "ASHUTOSH KUMAR", "SANTOSH KUMAR", 97, 0], "R": 15844}, {"C": ["R190810097049", "PAWAN", "LAL MOHAN SINGH", 43], "R": 16356}, {"C": ["R190810097048", "NITISH KUMAR", "JANKI DAS", "ANJU DEVI", 1], "R": 15844}, {"C": ["R190810097047", 48, "YOGENDRA VERMA", "KAMLA DEVI", 0], "R": 15844}, {"C": ["R190810097046", "GAUTAM KR PRASAD", "SANJAY PRASAD", 46], "R": 16356}, {"C": ["R190810097045", "AVINASH KUMAR", "TUNTUN KUMAR", 18, 0], "R": 16324}, {"C": ["R190810097044", "AMRITA KUMARI", 1, "ANIL KUMAR TIWARI", "VIDYA DEVI", 2], "R": 15840}, {"C": ["R190810097043", "NIRMA KUMARI", "UPENDRA YADAV", "Sarita Devi", 0], "R": 15844}, {"C": ["R190810097042", "SHIVAM KUMAR", 0, "MUNDRIKA SINGH", 63, 2], "R": 15840}, {"C": ["R190810097041", "KRISHNAKANT KUMAR"], "R": 16380}, {"C": ["R190810097040", "RITIKESH RAJ", "AJIT KUMAR", "CHETNA DEVI", 0], "R": 15844}, {"C": ["R190810097039", "PINTU KUMAR", "DASHARATH SINGH", "SHANTI DEVI"], "R": 16356}, {"C": ["R190810097038", "RAY SAHEB", "KOULESHVAR PRASAD", 11], "R": 16356}, {"C": ["R190810097037", "BISHWAJEET KUMAR", "RAMJEE SINGH", "SHARADA DEVI"], "R": 16356}, {"C": ["R190810097036", 1, "sunil kumar tiwari", "MAYA DEVI", 2], "R": 15844}, {"C": ["R190810097035", "SARVAJIT KUMAR", "SAGAR SINGH", 11, 0], "R": 15844}, {"C": ["R190810097034", 37, "RAMJEET RAY", "YASHODA DEVI"], "R": 16356}, {"C": ["R190810097033", "BALBIR KUMAR", "DHALAI MANDAL", "PREMLATA DEVI"], "R": 16356}, {"C": ["R190810097032", 0, "UPENDRA PRASAD VERMA", "lakho devi"], "R": 16356}, {"C": ["R190810097031", 22, "SANTOSH SAH", 63, 2, 1, 8, 8, 0], "R": 3716}, {"C": ["R190810097030", "RUPESH KUMAR", "BHAGWAN SAH", 73], "R": 16356}, {"C": ["R190810097029", "MANISH KUMAR", "VINOD SHARMA", "URAMILA DEVI", 0, 0, 3, 11, 1], "R": 3716}, {"C": ["R190810097028", "Utpal kant kumar", "DILIP YADAV", "SONAJHARI DEVI"], "R": 16356}, {"C": ["R190810097027", "SUMIT KUMAR", "MANOJ KUMAR", "MANITA DEVI"], "R": 16356}, {"C": ["R190810097026", "RAMNIRANJAN KUMAR", "RAM KUMAR PRASAD", 12], "R": 16356}, {"C": ["R190810097025", "RAJA KUMAR", "SANJAY MALAKAR", 15], "R": 16356}, {"C": ["R190810097024", 31, "SHARAD CHANDRA BIPIN", "BABITA DEVI", 2], "R": 15844}, {"C": ["R190810097023", "NITESH KUMAR", "MADESHVAR VERMA", "GANGEETA DEVI", 0], "R": 15844}, {"C": ["R190810097022", "BANTI KUMAR", "PANKAJ PASWAN", "GEETA DEVI", 1], "R": 15844}, {"C": ["R190810097021", "AMIT KUMAR", "AJAY YADAV", "RAMJHRI DEVI", 0], "R": 15844}, {"C": ["R190810097020", "VIKASH KUMAR PAL", "Vimal kumar pal", "GUDDY DEVI"], "R": 16356}, {"C": ["R190810097019", 31, "BALISTER SINGH", "SAKUNTALA DEVI", 7, 1, 8, 2, 8, 0], "R": 3204}, {"C": ["R190810097018", "AMRIT KUMAR", 4, "RANI DEVI", 0], "R": 15844}, {"C": ["R190810097017", "SIKENDRA BAITHA", "CHULHAI BAITHA", "BHAGWATI DEVI", 10, 1], "R": 15812}, {"C": ["R190810097016", "ANKIT RANJAN", "DINESH PRASAD", 56, 0], "R": 15844}, {"C": ["R190810097015", "ROBIN KUMAR", 62, "ASHA DEVI", 1, 0, 1], "R": 15748}, {"C": ["R190810097014", "MITHILESH KUMAR", "Ramsagar Prasad", 1, 0], "R": 15844}, {"C": ["R190810097013", 65, "GAURISHANKAR SAH", "RAMBHA DEVI"], "R": 16356}, {"C": ["R190810097012", 23, "PRADIP DUBEY", "NIKKI DEVI", 11, 2], "R": 15812}, {"C": ["R190810097011", "NITESH KUMAR", "YAMUNA SINGH", 23], "R": 16356}, {"C": ["R190810097010", "LAXMI KUMAR", "BALIRAM SAH", 40, 0], "R": 15844}, {"C": ["R190810097009", "RAVIRANJAN KUMAR", "CHHOTELAL PRASAD", 31], "R": 16356}, {"C": ["R190810097008", 23, "RAJA RAM MAHATO", 13], "R": 16356}, {"C": ["R190810097007", "LAV KUMAR", "LALBABU PRASAD", "PRABHA DEVI", 0, 3, 11, 1], "R": 3780}, {"C": ["R190810097006", "RAVIKANT KUMAR", "RAM PRAKASH SHARMA", 90, 2], "R": 15844}, {"C": ["R190810097005", 98, "BIJENDRA VERMA", "LALPARI DEVI", 0], "R": 15844}, {"C": ["R190810097004", "PANKAJ KUMAR PATEL", "VISHWAMOHAN SINGH", "MANTI DEVI"], "R": 16356}, {"C": ["R190810097003", "SUMIT KUMAR", "MADAN SINGH", "SHANTI DEVI"], "R": 16356}, {"C": ["R190810097002", "SHYAM SUNDAR KUMAR SAH", "RAJDEV SAH", 66], "R": 16356}, {"C": ["R190810097001", 56, "MADAN KUMAR", "BABITA DEVI"], "R": 16356}, {"C": ["R190810097000", "ADITYA PRAKASH", "PINTU LAL", 49], "R": 16356}, {"C": ["R190810096999", "NITISH KUMAR", "MANOJ LAL", "DARMAVATI DEVI"], "R": 16356}, {"C": ["R190810096998", "SOLU KUMAR", "RAM BABU RAM", "PRABHAVTI DEVI"], "R": 16356}, {"C": ["R190810096997", "ABHYASH PASWAN", "DEEWANATH PASWAN", "MEERA DEVI", 10, 1, 10], "R": 11492}, {"C": ["R190810096996", "BIJENDRA SINGH", "BHOLA SINGH YADAV", "minta devi", 0], "R": 15844}, {"C": ["R190810096995", 65, "UMESH SINGH", 35], "R": 16356}, {"C": ["R190810096994", "PRABHAT KUMAR GIRI", "SANTOSH GIRI", "SARASWATI DEVI", 3], "R": 15844}, {"C": ["R190810096993", "VIMAL KUMAR", "BIRENDRA SAH", "BABITA DEVI", 3, 0, 11], "R": 11492}, {"C": ["R190810096992", "AKHILESH KUMAR", "BHAGWANI MANDAL", "SHEELA DEVI"], "R": 16356}, {"C": ["R190810096991", "JITENDRA KUMAR YADAV", "RAVINDRA YADAV", "PRAMEELA DEVI"], "R": 16356}, {"C": ["R190810096990", "RAM CHARAN SAH", "ROHIT SAH", "PHULO DEVI"], "R": 16356}, {"C": ["R190810096989", "PINTU KUMAR", "INDRADEO CHOUDHARY", "SAROJANI DEVI", 1], "R": 15844}, {"C": ["R190810096988", "VIJAY KUMAR", "BIRENDRA KUMAR", "Binda Devi"], "R": 16356}, {"C": ["R190810096987", "NITISH KUMAR", "HARENDRA PRASAD", "RAMAVATI DEVI", 0], "R": 15844}, {"C": ["R190810096986", "AMIT RAJ", "KAUSHLENDRA PRASAD", 12], "R": 16356}, {"C": ["R190810096985", "KHUSHBOO PERVEEN", 1, "MD JAHANGIR", "SONI KHATOON"], "R": 16352}, {"C": ["R190810096984", "BISHINUDEV KUMAR", 0, "RAJ KUMAR SAW", "SOBHA DEVI"], "R": 16352}, {"C": ["R190810096983", "DIPIKA KUMARI", 1, "NANDJEE PANDEY", "MALTI DEVI", 7, 1, 11, 2, 12], "R": 11392}, {"C": ["R190810096982", "CHANDAN RAM", 0, "AWDHESH RAM", "AANMUNI DEVI", 1], "R": 15840}, {"C": ["R190810096981", "ANSHU KUMAR", "RAMASHISH SINGH", "SHANTI KUNWAR", 0], "R": 15844}, {"C": ["R190810096980", 69, 1, "THAKUR BIND", "SHIV DULARI DEVI"], "R": 16352}, {"C": ["R190810096979", "OJHA MAMTA DWARIKA PRASAD", "DWARIKA PRASAD", "INDU DEVI", 2], "R": 15844}, {"C": ["R190810096978", "MD SADRUDDIN MANSURI", 0, "MD NAIM MANSURI", "ASHMA KHATOON", 0], "R": 15840}, {"C": ["R190810096977", "RAKESH KUMAR", "RAVINDRA SINGH", "KUMARI DEVI"], "R": 16356}, {"C": ["R190810096976", "SONU KUMAR PAL", "RAMLAKHAN PAL", 85], "R": 16356}, {"C": ["R190810096975", 0, "RAMNARAYAN SINGH", "GEETA DEVI"], "R": 16356}, {"C": ["R190810096974", "KIRAN KUMARI", 1, "GYANESHVAR PRASAD SINGH", "KAMLA DEVI"], "R": 16352}, {"C": ["R190810096973", "NEHA KUMARI", "AJAY KUMAR SINGH", 18], "R": 16356}, {"C": ["R190810096972", "KIRAN KUMARI", "KAMESHWAR SINGH", 23], "R": 16356}, {"C": ["R190810096971", "NIMISHA KUMARI", "UPENDRA BIND", "VIDYAWATI DEVI"], "R": 16356}, {"C": ["R190810096970", "UDAY NARAYAN SINGH", 0, "CHANDRA DHAN SINGH", "SUMITRA DEVI"], "R": 16352}, {"C": ["R190810096969", "AKHILESH KUMAR", "RAJENDRA PRASAD", 31], "R": 16356}, {"C": ["R190810096968", "DIPU KUMAR", "BREEJ KHARWAR", 21, 5, 0], "R": 16260}, {"C": ["R190810096967", "GUPTESHWAR KUMAR", "SUKHDEV SHAH", "TARAMUNI DEVI"], "R": 16356}, {"C": ["R190810096966", "RAGHUBIR KUMAR", "KESHAV SINGH", "ZEERA DEVI"], "R": 16356}, {"C": ["R190810096965", "NITISH KUMAR", "CHHANGUR YADAV", "NILAM DEVI"], "R": 16356}, {"C": ["R190810096964", "ABHAY SINGH", "SATENDAR SINGH", "SANDHYA KUNWAR"], "R": 16356}, {"C": ["R190810096963", "IRSAD HUSSAIN", "ALIMUDDIN HUSSAIN", "NAIMUN KHATUN"], "R": 16356}, {"C": ["R190810096962", "JAYGOVIND MISHRA", "VIDYADHAR MISHRA", "MAMATA MISHRA", 2], "R": 15844}, {"C": ["R190810096961", "JAYNARAYAN SINGH", "MUNNA SINGH", "SABITA KUMARI", 0], "R": 15844}, {"C": ["R190810096960", 98, "MUNNA RAM", "SANPHULA DEVI", 1], "R": 15844}, {"C": ["R190810096959", "BALMEEKI KUMAR", "RAMCHANDAR PRAJAPTI", "JAGWATA KUNWAR", 0], "R": 15844}, {"C": ["R190810096958", "RISHIKUMAR SINGH", "GORAKH SINGH", "AARTI DEVI"], "R": 16356}, {"C": ["R190810096957", "NAGDEV KUMAR", "HARIBANSH SINGH", 36], "R": 16356}, {"C": ["R190810096956", "MUKESH KUMAR SINGH", "SANJAY KUMAR SINGH", "SAROJA DEVI"], "R": 16356}, {"C": ["R190810096955", "brajesh kumar", "VAKIL SINGH", 33], "R": 16356}, {"C": ["R190810096954", 76, "HARENDRA SINGH", "PARVATI DEVI"], "R": 16356}, {"C": ["R190810096953", "AMARJIT KUMAR SINGH", "RAM AANAT SINGH", "DHIRJA DEVI"], "R": 16356}, {"C": ["R190810096952", "VIKASH KUMAR SINGH", "KASHINATH SINGH", "BUDHIYA DEVI"], "R": 16356}, {"C": ["R190810096951", 90, "HARENDRA PRASAD", "MEERA DEVI", 0, 3, 11], "R": 11972}, {"C": ["R190810096950", "RAJ KUMAR", "MANOJ KUMAR", "KAUSHLAYA DEVI", 1], "R": 15844}, {"C": ["R190810096949", "SHIV DAYAL RANJAN", "SATYNAM KUMAR", "RIBHA DEVI"], "R": 16356}, {"C": ["R190810096948", "JAVED AKHTER", "MD KASHIM ANSARI", "NUZHAT PRAWEEN", 0], "R": 15844}, {"C": ["R190810096947", 48, "SHYAM BABU YADAV", 89], "R": 16356}, {"C": ["R190810096946", "RANJEET KUMAR", "KARIMAN MAHTO", "LALTI DEVI"], "R": 16356}, {"C": ["R190810096945", "BHASKAR KUMAR", "RAMANUJ MAHTO", "minta devi"], "R": 16356}, {"C": ["R190810096944", "LALU KUMAR", "VINDESHWAR YADAV", "MALTI DEVI"], "R": 16356}, {"C": ["R190810096943", "NITISH KUMAR", "AKHILESH KUMAR", "Belmanti Devi"], "R": 16356}, {"C": ["R190810096942", "DEEPAK KUMAR", "SUBHASH PRASAD SINGH", "SIYAKANTI KUMARI"], "R": 16356}, {"C": ["R190810096941", "HANUMAN SINGH", "SHRIRAM SINGH", "JAMURTA DEVI", 5, 11, 12], "R": 11972}, {"C": ["R190810096940", "JYOTI PRAKASH SINGH", "KAMENDRA SINGH", 31], "R": 16356}, {"C": ["R190810096939", "SARJU BIND", "HAWALDAR BIND", "BHAGAMANI DEVI"], "R": 16356}, {"C": ["R190810096938", "PRAKASH BIND", "BIHARI BIND", "JANKI DEVI"], "R": 16356}, {"C": ["R190810096937", "ABHINAV RAJ DHIRU", "ARJUN PRASAD BHARTI", "TUSHA DEVI", 1], "R": 15844}, {"C": ["R190810096936", "ANIL PAL", "SAMBHU PAL", "ASTORNA DEVI", 0], "R": 15844}, {"C": ["R190810096935", "MUKESH KUMAR", "RAM GAHAN PRAJAPATI", "PRAMILA DEVI"], "R": 16356}, {"C": ["R190810096934", "MERAJ ANSARI", "RIYAJUDDIN ANSARI", "JUBAIDA BIBI"], "R": 16356}, {"C": ["R190810096933", "MD SAIF ALI", "MD SUBAHAN ALI", "RABIYA KHATUN"], "R": 16356}, {"C": ["R190810096932", "PINTU KUMAR", "SHYAM BIHARI SETH", "DHARMSHILA DEVI"], "R": 16356}, {"C": ["R190810096931", "MITHILESH KUMAR", "SHAMBHU SINGH", "ASHA DEVI"], "R": 16356}, {"C": ["R190810096930", "dhananjay kumar", "RAM CHANDRA SINGH", "UMARAVATI DEVI"], "R": 16356}, {"C": ["R190810096929", "RAVISH KUMAR", "RAMDHYAN SINGH", "SARSWATI DEVI"], "R": 16356}, {"C": ["R190810096928", 74, "RAMESHWAR SINGH", "HIRAMUNI DEVI"], "R": 16356}, {"C": ["R190810096927", "MD TAUHID ANSARI", "MD ISRAR ALAM", "RUKSHANA BIBI"], "R": 16356}, {"C": ["R190810096926", "AKHILESH KUMAR", "SHAMBHU SINGH", "ASHA DEVI"], "R": 16356}, {"C": ["R190810096925", 94, "VIJAY SINGH", "GIRAJA DEVI"], "R": 16356}, {"C": ["R190810096924", 51, "UPENDRA BIND", "VIDHYAWATI DEVI"], "R": 16356}, {"C": ["R190810096923", 10, "UJIYAR SINGH", "BIJANTA DEVI"], "R": 16356}, {"C": ["R190810096922", "MD KAMRAN AHMAD", "Md Mozibul Rahman", "SAMIMA KHATUN"], "R": 16356}, {"C": ["R190810096921", "SHAKIL ANSARI", "MD KLAMUDDIN ANSARI", "SARIFAN BEGAM", 0], "R": 16324}, {"C": ["R190810096920", "AKASH KUMAR", "KRISHNA KUMAR SINGH", "PARMILA DEVI", 2], "R": 15844}, {"C": ["R190810096919", "DEEPAK TIWARI", "RAMASHRAY TIWARI", "VIMLA TIWARI"], "R": 16356}, {"C": ["R190810096918", 23, "ARVIND SINGH", 56], "R": 16356}, {"C": ["R190810096917", "ARJUN KUMAR", "YAMUNA KEVAT", 11, 0], "R": 15844}, {"C": ["R190810096916", 9, "NARENDRA RAM", "KRISNA DEVI", 1], "R": 15844}, {"C": ["R190810096915", "ANSHU KUMAR GUPTA", "VIJAY KUMAR", "LAXMINA DEVI", 0], "R": 15844}, {"C": ["R190810096914", "DHEERAJ KUMAR", "ARVIND SHARMA", "UMRAVTI DEVI", 3], "R": 15844}, {"C": ["R190810096913", "AMARNATH PASWAN", "DHARMRAJ PASWAN", "JUGAL KISHOR DEVI", 1], "R": 15844}, {"C": ["R190810096912", "ASHOK KUMAR SINGH", "RADHA KRISHANA SINGH", "KALAWATI DEVI", 0], "R": 15844}, {"C": ["R190810096911", 10, "HARENDRA SINGH", "SUMITRA DEVI"], "R": 16356}, {"C": ["R190810096910", "AJIT KUMAR PANDEY", "UDAY NARAYAN PANDEY", "MIRA DEVI", 2], "R": 15844}, {"C": ["R190810096909", "RAVI PRAKASH SINGH", "BACHAN SINGH", 12], "R": 16356}, {"C": ["R190810096908", "SHAGUFTA YASMIN", 1, "MD ISRAR ANSARI", "RABIYA KHATUN", 0], "R": 15840}, {"C": ["R190810096907", "GAJALA PRAVEEN", "MD IFTEKHAR ANSARI", "JARINA KHATUN"], "R": 16356}, {"C": ["R190810096906", "ARTI KUMARI JAISWAL", "KASHINATH SAH", 21], "R": 16356}, {"C": ["R190810096905", 69, "UCHIT CHAUDHARY", 56, 3], "R": 15844}, {"C": ["R190810096904", "MD SUHAIL ANSARI", 0, "MUSTAFA ANSARI", "KHADEEJA BEGAM", 0], "R": 15840}, {"C": ["R190810096903", "MD RAJA ANSARI", "MD ALI ANSARI", "RAJIYA BIBI"], "R": 16356}, {"C": ["R190810096902", "EKLAKH ANSARI", "RUSTAM ANSARI", "JULEKHA BIBI"], "R": 16356}, {"C": ["R190810096901", "MANISH KUMAR SHARMA", "MAHENDR SHARMA", "DURGAVATI DEVI", 3, 3, 11], "R": 11492}, {"C": ["R190810096900", "AANAND KUMAR SHARMA", "RAJENDRA PRASAD SHARMA", 35], "R": 16356}, {"C": ["R190810096899", "ABHAY KUMAR PASWAN", "SHIVJI PASWAN", "MUNNI DEVI", 1], "R": 15844}, {"C": ["R190810096898", 94, "RAVINDRA KUMAR", "NIRA SINHA", 0], "R": 15844}, {"C": ["R190810096897", "MD SHABBIR ALAM", "MD JAMIL ANSARI", "YASMIN KHATOON"], "R": 16356}, {"C": ["R190810096896", "MD SAQUIB ALAM", "MD JAMIL"], "R": 16372}, {"C": ["R190810096895", "ANSARI CHAND RIYAZUDDIN", "MO RIYAZUDDIN", "HAJARA KHATOON"], "R": 16356}, {"C": ["R190810096894", "KUMAR ABHISHEK", "RAMESH YADAV", 31], "R": 16356}, {"C": ["R190810096893", 23, "SURENDRA SINGH", 33], "R": 16356}, {"C": ["R190810096892", "ARVIND KUMAR", "KAMALESH PRASAD", "KAMALAWATI DEVI"], "R": 16356}, {"C": ["R190810096891", "PRADUMAN KUMAR", "KOMAL SINGH", "VINDHYACHALI DEVI", 11, 12], "R": 12004}, {"C": ["R190810096890", "RAVIRANJAN KUMAR", "MUNNA SINGH", "SUMITRA DEVI"], "R": 16356}, {"C": ["R190810096889", "MANISH KUMAR", "ABHAY NARAYAN SINGH YADAV", "RADHIKA DEVI"], "R": 16356}, {"C": ["R190810096888", "RITESH KUMAR", "DHANJI SAH", 73], "R": 16356}, {"C": ["R190810096887", "ASHISH KUMAR GUPTA", "MOTI CHAND GUPTA", "SARSWATI DEVI"], "R": 16356}, {"C": ["R190810096886", "SNEHA KUMARI", 1, "SURYANATH PAL", 33], "R": 16352}, {"C": ["R190810096885", "ADITYA KUMAR PANDEY", 0, "PARAMHANS PANDEY", "SMITA PANDEY", 2], "R": 15840}, {"C": ["R190810096884", "AAKASH KUMAR", "NAND KUMAR PASWAN", "DAULATO DEVI", 1], "R": 15844}, {"C": ["R190810096883", 77, "Shivdharee Paswan", "VIMALA DEVI"], "R": 16356}, {"C": ["R190810096882", "PUSHPA KUMARI", 1, "SANJAY PANDEY", "PREMA DEVI", 2], "R": 15840}, {"C": ["R190810096881", "DHEERAJ PANDEY", 0, "RAMESHWAR PANDEY", "MANSHA DEVI"], "R": 16352}, {"C": ["R190810096880", 37, "RADHESHYAM SINGH", "TARAMUNNI DEVI", 0], "R": 15844}, {"C": ["R190810096879", "DEEPAK KUMAR", "RAMESH SINGH", "Asha Sinha"], "R": 16356}, {"C": ["R190810096878", "HIMANSHU KUMAR", "SANJAY KUMAR", 73, 3], "R": 15844}, {"C": ["R190810096877", "MD SAJID ANSARI", "MD YAKUB ANSARI", "JOHRA KHATUN", 0], "R": 15844}, {"C": ["R190810096876", "MURALI KUMAR", "ASHOK RAI", "SAROJANA DEVI"], "R": 16356}, {"C": ["R190810096875", "RITESH KUMAR", "PARAS NATH CHAUDHARY", 11], "R": 16356}, {"C": ["R190810096874", "SAROJ KUMAR SHARMA", "SHRIRAM SHARMA", "SHYAMALA DEVI"], "R": 16356}, {"C": ["R190810096873", "SONU GOSWAMI", "DWARIKA GOSWAMI", "ANJU DEVI"], "R": 16356}, {"C": ["R190810096872", "RAJNISH KUMAR", "RAMESHWAR SINGH", 12], "R": 16356}, {"C": ["R190810096871", 1, "UMESH PRASAD", "MAYA DEVI", 3, 11], "R": 12004}, {"C": ["R190810096870", "PRABHASH KUMAR", "ARUN PRASAD YADAV", "YASODHA DEVI"], "R": 16356}, {"C": ["R190810096869", "RAKESH KUMAR", "YAMUNA PASWAN", "CHANWA DEVI", 1], "R": 15844}, {"C": ["R190810096868", "VIJAY KUMAR", "OM PRAKASH PASWAN", "RAM PYARI DEVI"], "R": 16356}, {"C": ["R190810096867", "Dilip Kumar", "RAM PUKAR SINGH", 15, 0], "R": 15844}, {"C": ["R190810096866", "JITENDRA KUMAR CHAUDHARY", "GUNA CHAUDHARY", "LAL PATI DEVI", 1], "R": 15844}, {"C": ["R190810096865", "MD IRSHAD ALAM", "MD TAIYAB", "AFSANA BEGAM", 0], "R": 15844}, {"C": ["R190810096864", "ROHIT RAJ", "HANSH NARAYAN", "ANJU DEVI"], "R": 16356}, {"C": ["R190810096863", 23, "SANESH SHAH", 5], "R": 16356}, {"C": ["R190810096862", "SHANISH RAJ", "KAMESHWAR PRASAD GUPTA", 31], "R": 16356}, {"C": ["R190810096861", "JITENDRA KUMAR", "PYARE GOPE", 7, 7, 1, 12, 13], "R": 11908}, {"C": ["R190810096860", 31, "MAHESH PRASAD", 36, 5, 0, 4, 14], "R": 11908}, {"C": ["R190810096859", "ABHAY KUMAR MOURYA", "NITHOHAR SINGH", "MEERA DEVI", 13, 15], "R": 12004}, {"C": ["R190810096858", 37, "RAMJANAM  PASWAN", 63, 0, 14, 1, 16], "R": 11460}, {"C": ["R190810096857", 21, "Birendra  Prasad", 38, 0], "R": 15844}, {"C": ["R190810096856", "SURAJ KUMAR", "SRI DHANRAJ  YADAV", "PANCHOLA DEVI"], "R": 16356}, {"C": ["R190810096855", "BAIJU KUMAR YADAV", "AWADESH YADAV", "RAJMUNI DEVI", 13, 1, 17], "R": 10980}, {"C": ["R190810096854", 30, "PAPPU KUMAR", 33, 15, 0, 18], "R": 10980}, {"C": ["R190810096853", "NIKESH KUMAR", "LAKSHMAN SAH", "RADHIKA DEVI", 7, 1, 4, 0, 0], "R": 3716}, {"C": ["R190810096852", 13, "PRAMOD KUMAR CHAURASIA", 15], "R": 16356}, {"C": ["R190810096851", "SAMMI KUMARI", 1, "UMASHANKAR RAY", "PRATIMA DEVI"], "R": 16352}, {"C": ["R190810096850", "KUMAR GAURAV", 0, "SHANKAR KUMAR", 33, 2], "R": 15840}, {"C": ["R190810096849", "ARYAN KUMAR", "PRADEEP KUMAR VERMA", "SUNITA SINHA"], "R": 16356}, {"C": ["R190810096848", "KARAN KUMAR", "RAM BINOD SINGH", 16], "R": 16356}, {"C": ["R190810096847", "MANISH KUMAR", "MOHAN PRASAD SONI", "ANITA SONI", 0], "R": 15844}, {"C": ["R190810096846", 51, "RAMKUMAR SINGH", "PRAMILA DEVI"], "R": 16356}, {"C": ["R190810096845", "SANJAY KUMAR", "RAMNATH RAM", 16, 1], "R": 15844}, {"C": ["R190810096844", 21, "TILAK RAUT", "RADHA DEVI", 0], "R": 15844}, {"C": ["R190810096843", "MD TABREJ ALAM", "MD MAJID MANSURI", "MOKILAN BIBI"], "R": 16356}, {"C": ["R190810096842", "AMIT KUMAR", "LALIT KUMAR SINGH", 73], "R": 16356}, {"C": ["R190810096841", "SURAJ KUMAR", "NANDKISHOR MAHTO", "NAGINA DEVI"], "R": 16356}, {"C": ["R190810096840", "GYANGAURAV KUMAR", "DIWAKAR KUMAR SHRIVASTAV", "KUMKUM DEVI", 2], "R": 15844}, {"C": ["R190810096839", "ANIKET KUMAR", "SANTOSH KUMAR", 35], "R": 16356}, {"C": ["R190810096838", "AKHILESH KUMAR", "SAHESH SAH", 13, 0], "R": 15844}, {"C": ["R190810096837", "SURAJ KUMAR", "GOPAL SINGH", 46], "R": 16356}, {"C": ["R190810096836", "AJIT KUMAR", "GANESH MAHTO", 12], "R": 16356}, {"C": ["R190810096835", "GUDDU KUMAR", "LALBIHARI RAM", "SUNITA KUMARI", 1], "R": 15844}, {"C": ["R190810096834", "GAURAV KUMAR", "SUNIL JHA", "SINDHU DEVI", 2], "R": 15844}, {"C": ["R190810096833", "Ayush Raj", "GAURI SHANKAR GUPTA", 5, 0], "R": 15844}, {"C": ["R190810096832", "KAJAL KUMARI", 1, "RAVINDRA SAHANI", "MUNNI DEVI"], "R": 16352}, {"C": ["R190810096831", 56, 0, "RAJ KUMAR MAHTO", "SARASVATI DEVI"], "R": 16352}, {"C": ["R190810096830", "SANI KUMAR TIWARI", "DILIP KUMAR TIWARI", "BABITA DEVI", 2], "R": 15844}, {"C": ["R190810096829", "PRAVIN KUMAR BHARTI", "RAM NARESH RAM", "PRABHAWATI DEVI", 1], "R": 15844}, {"C": ["R190810096828", "MD KALIM", "MD SARFUDDIN", "SAKINA KHATOON", 0], "R": 15844}, {"C": ["R190810096827", 48, "BHAGIRATH SAH", "LALTI DEVI"], "R": 16356}, {"C": ["R190810096826", "DURGESH KUMAR", "SURESH SHARMA", "MUNNI DEVI"], "R": 16356}, {"C": ["R190810096825", 21, "ASHARPHI SAH", "GEETA DEVI"], "R": 16356}, {"C": ["R190810096824", 96, "SUNIL THAKUR", "Sarita Devi"], "R": 16356}, {"C": ["R190810096823", 23, "ASHOK RAJAK", 38, 1], "R": 15844}, {"C": ["R190810096822", "MD SAROJ", "GUL MOHAMMAD", "SAMIRUL KHATOON", 2], "R": 15844}, {"C": ["R190810096821", "VICKY KUMAR", "Naresh Thakur", "RICHA KUMARI", 0], "R": 15844}, {"C": ["R190810096820", "VIKRANT KUMAR", "SHAMBHU KUMAR SINGH", "HEERA DEVI", 2], "R": 15844}, {"C": ["R190810096819", 32, "SURENDRA SHARMA", "KRISHNA DEVI"], "R": 16356}, {"C": ["R190810096818", "RANJAN KUMAR", "UMESH RAY", "SAVITA DEVI", 0], "R": 15844}, {"C": ["R190810096817", "SURAJ KUMAR", "VISHNU PASWAN", 38, 1], "R": 15844}, {"C": ["R190810096816", "GUDDU KUMAR", "SATYANARAYAN RAI", 71, 0], "R": 15844}, {"C": ["R190810096815", "ABID RABBANI", "MD SUBHAN RABBANI", "SHAIRA BANO"], "R": 16356}, {"C": ["R190810096814", "Vikram kumar", "MAHADEV SAH", 40], "R": 16356}, {"C": ["R190810096813", 77, "BINDA SINGH", "NUTAN KUMARI"], "R": 16356}, {"C": ["R190810096812", "KARGIL KUMAR", "BHARAT SAH", "PRAMILA DEVI"], "R": 16356}, {"C": ["R190810096811", "NIRAJ KUMAR", "MALIK PASWAN", "RESHAMI DEVI", 1], "R": 15844}, {"C": ["R190810096810", "PAWAN KUMAR", "BIGAN MAHTO", "MAHOKHIYA DEVI", 0], "R": 15844}, {"C": ["R190810096809", "DEENBANDHU KUMAR", "JAYLAL CHAUCHARY", 49, 1], "R": 15844}, {"C": ["R190810096808", "LALIT KUMAR", "SITARAM YADAV", "INDU DEVI", 0], "R": 15844}, {"C": ["R190810096807", "ASHUTOSH KUMAR SINGH", "SH. RAJENDRA KUMAR SINGH", "MRS. CHINTA DEVI", 5, 0, 9, 19, 1], "R": 3716}, {"C": ["R190810096806", "DHARMSHILA KUMARI", 1, "RAMESH YADAV", "BASO DEVI", 1, 2, 20], "R": 11488}, {"C": ["R190810096805", "PRAMOD KUMAR", 0, "SHIV PRASAD", "LAKSHMI DEVI", 0], "R": 15840}, {"C": ["R190810096804", "BAIJU KUMAR", "SUNIL PRASAD", "SVITA DEVI"], "R": 16356}, {"C": ["R190810096803", "SANDEEP RAJ", "RAMESH KUMAR", 89], "R": 16356}, {"C": ["R190810096802", "PUNAM KUMARI", 1, "CHANDRIKA PRASAD", "NILAM DEVI"], "R": 16352}, {"C": ["R190810096801", "AMARJEET KUMAR", 0, "UMESH PASWAN", 49], "R": 16352}, {"C": ["R190810096800", 96, "TAPESBRA PANDIT", 73], "R": 16356}, {"C": ["R190810096799", "PRADUMAN KUMAR", "nagendra prasad", "LALMANI DEVI"], "R": 16356}, {"C": ["R190810096798", "NIRAJ KUMAR", "SATISH PRASAD", "SAROJ DEVI"], "R": 16356}, {"C": ["R190810096797", "INDRAJIT KUMAR", "NAGENDRA NATH YADAV", "BARTI DEVI"], "R": 16356}, {"C": ["R190810096796", "AMIT RAJ", "ASHOK KUMAR", "MADHU DEVI"], "R": 16356}, {"C": ["R190810096795", "DHARMVIR KUMAR", "RAJVALLAV YADAV", "JAYMANTI DEVI"], "R": 16356}, {"C": ["R190810096794", "VIDYA BHUSHAN KUMAR", "NEKHA PRASAD", "SHANTI DEVI"], "R": 16356}, {"C": ["R190810096793", "AJEET KUMAR", "SURENDRA CHAUDHARY", "KUNTI DEVI", 0, 1], "R": 15812}, {"C": ["R190810096792", 22, "AKHILESH PRASAD", 31, 0], "R": 15844}, {"C": ["R190810096791", "SUKHENDAR KUMAR", "RAJBALLABH PRASAD", "KUNTI DEVI"], "R": 16356}, {"C": ["R190810096790", "PRIYANKA KUMARI", 1, "VIRENDRA PRASAD", "PRABHA DEVI"], "R": 16352}, {"C": ["R190810096789", "SEEMA KUMARI"], "R": 16380}, {"C": ["R190810096788", "DHIRENDRA KUMAR", 0, "BHOLA PRASAD", 94], "R": 16352}, {"C": ["R190810096787", "NAGENDRA SAPERA", "SANJAY SAPERA", 63, 1], "R": 15844}, {"C": ["R190810096786", "RAJENDRA KUMAR", "LALAN VIND", "DEVMANTI DEVI", 0], "R": 15844}, {"C": ["R190810096785", "SURAJ KUMAR", "ANJANI KUMAR", 18], "R": 16356}, {"C": ["R190810096784", "SURENDRA KUMAR", "RAM SOHAWAN PRASAD", "MAHAPATI DEVI"], "R": 16356}, {"C": ["R190810096783", "KAUSHAL KUMAR", "SHLOK PRASAD", "Sarita Devi"], "R": 16356}, {"C": ["R190810096782", 98, "RAMANUJ KUMAR", 49], "R": 16356}, {"C": ["R190810096781", "GAJENDRA KUMAR", "CHANDRA BHUSHAN PANDEY", 90, 2], "R": 15844}, {"C": ["R190810096780", "SUDHIR KUMAR", "KRISHNA PRASAD", "SULABH DEVI", 0], "R": 15844}, {"C": ["R190810096779", "BEAUTY KUMARI", 1, "VIMAL KUMAR PANDEY", "SUVIDHA DEVI", 2], "R": 15840}, {"C": ["R190810096778", "AMRITA KUMARI", "ANIL PRASAD KESHRI", "CHANCHLA DEVI", 0], "R": 15844}, {"C": ["R190810096777", 37, 0, "MAHESH PRASAD", 31], "R": 16352}, {"C": ["R190810096776", "SWATI ANAND", 1, "ARJUN KUMAR", 73], "R": 16352}, {"C": ["R190810096775", "PRADEEP KUMAR", 0, "GOBARDHAN MATHO", "RENUKA DEVI"], "R": 16352}, {"C": ["R190810096774", "DAMODAR KUMAR", "rambalak prasad", 35], "R": 16356}, {"C": ["R190810096773", "SATYENDRA KUAMR", "VIRENDRA RAY", 1, 5, 16, 21], "R": 11972}, {"C": ["R190810096772", "DHIRAJ KUMAR", "MAHESH RAY", 11], "R": 16356}, {"C": ["R190810096771", 22], "R": 16380}, {"C": ["R190810096770", "NIRAJ KUMAR", "GHANSHYAM PANDIT", "ABHILASHA DEVI", 2, 1, 15, 0, 0], "R": 3716}, {"C": ["R190810096769", "MD SHAHJAD", "MD MUBARAK", "MUNNA KHATOON", 1, 0, 17], "R": 16004}, {"C": ["R190810096768", "MANISH KUMAR YADAV", "CHAMRU YADAV", "MUNNI DEVI"], "R": 16356}, {"C": ["R190810096767", "CHANCHAL KUMAR SAH", "SHAMBHU SAH", "BULEE DEVI"], "R": 16356}, {"C": ["R190810096766", "PRIYANSHU SHARMA", "SAPAN SHARMA", "SAVITA DEVI"], "R": 16356}, {"C": ["R190810096765", "SHUBHAM KUMAR", "ABHAY MANDAL", 46], "R": 16356}, {"C": ["R190810096764", 48, "SUBODH YADAV", "SULEKHA DEVI"], "R": 16356}, {"C": ["R190810096763", "KUNDAN KUMAR SHARMA", "PARMANAND SHARMA", 3], "R": 15860}, {"C": ["R190810096762", "GULAM SARBAR", "MD MOIN", "ANJUM ARA", 2], "R": 15844}, {"C": ["R190810096761", "ASHARFI KUMAR RAY", "SUBODH RAY", "TARA DEVI", 1], "R": 15844}, {"C": ["R190810096760", "PANKAJ KUMAR PASWAN", "GAVESH PASWAN", "BINDO DEVI"], "R": 16356}, {"C": ["R190810096759", "SURAJ KUMAR", "SIRITH CHOUDHARY", 73, 2], "R": 15844}, {"C": ["R190810096758", "RAJ KUMAR", "RAM VILASH PASWAN", 21, 2, 1, 1], "R": 15748}, {"C": ["R190810096757", 6, "VIMAL DEV PANDIT", "RUKMANI DEVI", 3, 0, 0], "R": 15748}, {"C": ["R190810096756", "ROHIT KUMAR YADAV", "MANOJ KUMAR YADAV", 73], "R": 16356}, {"C": ["R190810096755", "MITHUN KUMAR RAM", "SIKANDAR RAM", "RUBY DEVI"], "R": 16356}, {"C": ["R190810096754", "NITISH KUMAR", "RAMANAND MAHTO", 47], "R": 16356}, {"C": ["R190810096753", "ANUJ KUMAR", "OM PRAKASH SAH", "SHELA DEVI"], "R": 16356}, {"C": ["R190810096752", "PANKAJ KUMAR", "SUDHEER KUMAR DAS", 18], "R": 16356}, {"C": ["R190810096751", "SURAJ KUMAR DAS", "NARAYAN DAS", "MALTI DEVI", 1], "R": 15844}, {"C": ["R190810096750", "NANDU KUMAR PASWAN", "UPENDRA  KUMAR PASWAN", "BECHANEE DEVI"], "R": 16356}, {"C": ["R190810096749", "PINTU KUMAR MANDAL", "MAKHAN MANDAL", 74, 2], "R": 15844}, {"C": ["R190810096748", "ABHAY KUMAR RAJAK", "PRAVESH RAJAK", "MADHU DEVI", 1], "R": 15844}, {"C": ["R190810096747", "RAJ KUMAR", "AKIL SHA", 15, 7, 1, 0], "R": 15748}, {"C": ["R190810096746", "MD TALIM", "MD. NAJIR", "MEHARJAN"], "R": 16356}, {"C": ["R190810096745", "GOVIND KUMAR SINGH", "JYOTISH PRASAD SINGH", 49], "R": 16356}, {"C": ["R190810096744", "RAVI ROSHAN KUMAR", "PRADEEP GUPTA", "CHUNNI DEVI"], "R": 16356}, {"C": ["R190810096743", "SUKHSAGAR KUMAR", "SUBOL SAH", "RANI DEVI"], "R": 16356}, {"C": ["R190810096742", 10, "RAM VILAS MAHTO", "GAYA DEVI"], "R": 16356}, {"C": ["R190810096741", "VISHNU KUMAR", "BALRAM BISHWAS", 33], "R": 16356}, {"C": ["R190810096740", 26, "MANOJ KUMAR PODDAR", "SUJATA DEVI"], "R": 16356}, {"C": ["R190810096739", "LALAN KUMAR", "BADDRI CHAUHAN", "patwa devi"], "R": 16356}, {"C": ["R190810096738", "AMAN KUMAR THAKUR", "RAJESH THAKUR", "PUSHPA DEVI"], "R": 16356}, {"C": ["R190810096737", "SUMIT KUMAR AGRAHARI", "GURU PRASAD AGRAHARI", "MADHU DEVI"], "R": 16356}, {"C": ["R190810096736", "MD SARFARAJ ALAM", "MD. NAUSAD ALI", "NASIMA KHATOON"], "R": 16356}, {"C": ["R190810096735", "KARTIC KUMAR", "SUNIL KUMAR", "SOVA DEVI"], "R": 16356}, {"C": ["R190810096734", "MD SHADAB RAZA", "MD. SAJJAD ALAM", "TABASSUAM JAHAN"], "R": 16356}, {"C": ["R190810096733", "Vikram kumar", "DHANANJAY MANDAL", "LAXMI DEVI"], "R": 16356}, {"C": ["R190810096732", "PUNAM KUMARI PASWAN", 1, "SUDHEER PASWAN", "KAMACHHIYA DEVI", 1], "R": 15840}, {"C": ["R190810096731", "LAXMI KUMARI", "SINHESHWAR PRASAD SINGH", "SANDHYA DEVI", 3], "R": 15844}, {"C": ["R190810096730", 35, 0, "SHIV SHANKAR PASWAN", "MEERA DEVI", 1], "R": 15840}, {"C": ["R190810096729", 77, "MAHESH SHARMA", 73], "R": 16356}, {"C": ["R190810096728", "GANESH KUMAR PASWAN", "SHANKAR PASWAN", "SUMITRA DEVI"], "R": 16356}, {"C": ["R190810096727", "AAYUSH KUMAR", "RAJ KUMAR RAUT", 97], "R": 16356}, {"C": ["R190810096726", "PRITAM KUMAR", "RAMOTAR MANDAL", "SAKUNA DEVI", 3], "R": 15844}, {"C": ["R190810096725", "AKHILESH KUMAR MANDAL", "RAJ KUMAR MANDAL", "DEVKI DEVI"], "R": 16356}, {"C": ["R190810096724", "VIKASH KUMAR PUSHPAM", "SURENDRA MAHTO", "Sarita Devi", 8, 0, 0], "R": 15748}, {"C": ["R190810096723", "GOVIND KUMAR MANDAL", "JAY PRAKASH MANDAL", "SUKUN DEVI"], "R": 16356}, {"C": ["R190810096722", "SUMIT KUMAR", "SURESH DAS", "MEERA DEVI", 1], "R": 15844}, {"C": ["R190810096721", "SUMIT KUMAR THAKUR", "SURESH PRASAD THAKUR", "MALA DEVI", 0], "R": 15844}, {"C": ["R190810096720", "SAMOL KUMAR", "LAXMI PRASAD CHOUHAN", 73], "R": 16356}, {"C": ["R190810096719", 21, "KAMAL KISHOR YADAV", "SUCHITRA DEVI"], "R": 16356}, {"C": ["R190810096718", "DEEPAK KUMAR", "NAGENDRA PRASAD SAH", 72], "R": 16356}, {"C": ["R190810096717", "NASIMA KHATUN", 1, "MD. IRFAN", "ROHILA KHATOON"], "R": 16352}, {"C": ["R190810096716", 1, 0, "BHOLA PRASAD SAH", 52], "R": 16352}, {"C": ["R190810096715", "MITHUN KUMAR BHAGAT", "PRITHWICHAND BHAGAT", "SUMITRA DEVI"], "R": 16356}, {"C": ["R190810096714", "SURAJ KUMAR", "RAVINDRA DAS", "SARMILA DEVI", 1], "R": 15844}, {"C": ["R190810096713", "KRISHNNANDAN KUMAR", "ANANDI DAS", "Hirda Devi"], "R": 16356}, {"C": ["R190810096712", "MD WAKAR ALAM", "SHEKH MANSUR ALAM", "TARINA KHATUN", 2], "R": 15844}, {"C": ["R190810096711", "AASHISH KUMAR", "PRAMOD SHARMA", "SAKUNA DEVI", 1], "R": 15844}, {"C": ["R190810096710", "RAJU MURMU", "JETHA MURMU", "MANJHLI HANSDA", 9, 3], "R": 15812}, {"C": ["R190810096709", "RAJNISH KUMAR", "PRAKASH SAH", "GYANI DEVI", 0], "R": 15844}, {"C": ["R190810096708", "VIVEK KUMAR SHARMA PAMPI", "BIRJU SHARMA", "CHAMPA DEVI"], "R": 16356}, {"C": ["R190810096707", "KRISHNA KUMAR CHOUHAN", "KANTLAL CHOUHAN", "KAMALI DEVI"], "R": 16356}, {"C": ["R190810096706", "SURAJ KUMAR", "PRAMANAND CHOUHAN", "SACHITA DEVI"], "R": 16356}, {"C": ["R190810096705", "RAVI RAUSHAN", "SRI AMIT KUMAR MANDAL", "SMT ANITA DEVI"], "R": 16356}, {"C": ["R190810096704", "NITIN KUMAR", "VINOD SAH", "NEELAM DEVI"], "R": 16356}, {"C": ["R190810096703", "ROSHAN KUMAR", "SUNIL ROY", "RADHA DEVI"], "R": 16356}, {"C": ["R190810096702", "AYUSH KUMAR MAHTO", "ADHIR KUMAR MAHTO", "RANI DEVI"], "R": 16356}, {"C": ["R190810096701", "NIRAJ KUMAR SHARMA", "PRADIP SHARMA", "PUSHPA DEVI", 3], "R": 15844}, {"C": ["R190810096700", "NIGAM KUMAR RAY", "SACHIN RAY", "MUNNI DEVI", 1], "R": 15844}, {"C": ["R190810096699", 69, 1, "DINESH PASWAN", 68], "R": 16352}, {"C": ["R190810096698", "MANISH KUMAR", 0, "MEGHNATH MAHTO", "HEMANTI DEVI", 6, 0], "R": 15808}, {"C": ["R190810096697", "KUMAR MANISH", "VINAY KUMAR", "CHINTA DEVI"], "R": 16356}, {"C": ["R190810096696", "ANKIT KUMAR", "ANIRUDH KUMAR MANDAL", "SAVITA KUMARI"], "R": 16356}, {"C": ["R190810096695", "RAHUL KUMAR DAS", "SUBOL DAS", "ANANDI DEVI"], "R": 16356}, {"C": ["R190810096694", 0, "MANOJ BHAGAT", 38], "R": 16356}, {"C": ["R190810096693", "PRAVIN KUMAR", "AJAY ROY", "RAMBHA DEVI"], "R": 16356}, {"C": ["R190810096692", "AMIT KUMAR", "RAJESH MUNI", "NITU DEVI"], "R": 16356}, {"C": ["R190810096691", "BABLI KUMARI", 1, "DEEPAK KUMAR SINGH", 38], "R": 16352}, {"C": ["R190810096690", "ANUJ KUMAR SINGH", 0, "SURESH PRASAD SINGH", "Putul Devi", 3], "R": 15840}, {"C": ["R190810096689", 10, "SUDIN PASWAN", "SAVITA DEVI", 1], "R": 15844}, {"C": ["R190810096688", "NEERAJ KUMAR RAJAK", "RAMANAND RAJAK", "SHANTI DEVI"], "R": 16356}, {"C": ["R190810096687", "MUKESH KUMAR", "VINOD CHAUDHARY", 31], "R": 16356}, {"C": ["R190810096686", "JOSNA KUMARI", 1, "RAMKISHAN PASWAN", "BIMLI DEVI"], "R": 16352}, {"C": ["R190810096685", "ANCHAL KUMARI", "NARESH PRASAD", "NUTAN DEVI", 4, 1], "R": 16260}, {"C": ["R190810096684", "BHAVESH RAJ", 0, "TRILOKI THAKUR", "NITU DEVI", 0], "R": 15840}, {"C": ["R190810096683", "DHRUV KUMAR MEHTA", "DINESH MEHTA", 49], "R": 16356}, {"C": ["R190810096682", "ASHWANI KUMAR RAJAK", "DILIP KUMAR RAJAK", 38, 1], "R": 15844}, {"C": ["R190810096681", "DEEPA KUMARI", 1, "SAROJ KUMAR SAH", "ANJALI DEVI", 11, 0, 0], "R": 15744}, {"C": ["R190810096680", "BIKRAM KUMAR", 0, "SHANKAR YADAV", 90], "R": 16352}, {"C": ["R190810096679", 31, "PRABHAT KUMAR MANDAL", "GURIYA DEVI"], "R": 16356}, {"C": ["R190810096678", "RITIK KUMAR", "VIDROHI YADAV", "PUNAM KUMARI"], "R": 16356}, {"C": ["R190810096677", "SHEKHAR KUMAR THAKUR", "DINESH THAKUR", "ANURADHA DEVI"], "R": 16356}, {"C": ["R190810096676", "ANIL KUMAR MANDAL", "UPENDRA MANDAL", 15], "R": 16356}, {"C": ["R190810096675", "FUL KUMAR MANDAL", "Ramdev mandal", "SUMITRA DEVI"], "R": 16356}, {"C": ["R190810096674", "DHARAMBEER  PASWAN", "BHOLA PASWAN", "KAREE DEVI", 1], "R": 15844}, {"C": ["R190810096673", "AMRITA  KUMARI", 1, "SUBODH KUMAR THAKUR", "DOLI DEVI", 2], "R": 15840}, {"C": ["R190810096672", "PRAKASH SAH", 0, "SUNIL SAH", "NILAM DEVI", 0], "R": 15840}, {"C": ["R190810096671", "MANOJ KUMAR MANDAL", "RAM BILAS MANDAL", 13, 3], "R": 15844}, {"C": ["R190810096670", 67, "PANCHLAL MANDAL", "SUKNI DEVI", 0], "R": 15844}, {"C": ["R190810096669", "AAKASH KUMAR TANTI", "SURESH PRASAD TANTI", "Lila Devi", 1], "R": 15844}, {"C": ["R190810096668", "Ayush Raj", "KAMESHWAR KARN", 45, 2], "R": 15844}, {"C": ["R190810096667", "ASHISH KUMAR", "SURYODAY CHAUHAN", 52, 0], "R": 15844}, {"C": ["R190810096666", "NEERAJ KUMAR", "PRAYAG THAKUR", 73], "R": 16356}, {"C": ["R190810096665", "CHANCHAL KUMAR SHARMA", "SHANKAR SHARMA", "PRATIMA DEVI"], "R": 16356}, {"C": ["R190810096664", "VIJAY HEMBRAM", "BICCHU HEMBRAM", "TALAKURI MURMU", 3], "R": 15844}, {"C": ["R190810096663", "KARAN KUMAR PODDAR", "SHAMBHU PODDAR", "Sarita Devi", 0], "R": 15844}, {"C": ["R190810096662", "SAJAN KUMAR DAS", 53, "TARA DEVI"], "R": 16356}, {"C": ["R190810096661", "NAWEEN KUMAR GOSWAMI", "BRAJNANDAN GOSWAMI", "ASHA DEVI", 2], "R": 15844}, {"C": ["R190810096660", "KRISHNA KUMAR YADAV", "KANAKLAL YADAV", "Prmila Devi", 0], "R": 15844}, {"C": ["R190810096659", "SONIPRIYA KUMARI", 1, "DINESH YADAV", "JANKI DEVI"], "R": 16352}, {"C": ["R190810096658", "MD SHAMSHER ANSARI", 0, "MD SIRAJUL ANSARI", "BIBI TASMIRA KHATUN"], "R": 16352}, {"C": ["R190810096657", "RAJ KAMAL KUMAR", "TUNTUN VISHWAS", 73], "R": 16356}, {"C": ["R190810096656", 57, "SURESH MANDAL", "PARVATI DEVI"], "R": 16356}, {"C": ["R190810096655", 7, "KAPURI MANDAL", "DAYAVATI DEVI"], "R": 16356}, {"C": ["R190810096654", "PINKU KUMAR", "LOGEN SINGH", 1], "R": 16356}, {"C": ["R190810096653", "GAUTAM KUMAR BISHWAS", "SATYANARAYAN BISHWAS", "NIRA DEVI"], "R": 16356}, {"C": ["R190810096652", "BAPPI KUMAR YADAV", "KAMALDEV YADAV", "SULEKHA DEVI"], "R": 16356}, {"C": ["R190810096651", "MANI BHUSAN MANISH", "SHASHI BHUSHAN MANDAL", 1], "R": 16356}, {"C": ["R190810096650", "SUJITI KUMARI", 1, "SAHDEV RAY"], "R": 16368}, {"C": ["R190810096649", "MITHUN KUMAR", 0, "KAILASH RAY", "SULEKHA DEVI"], "R": 16352}, {"C": ["R190810096648", "ANSHU KUMAR", "SANTOSH KUMAR BIND", 47], "R": 16356}, {"C": ["R190810096647", 94, "RAJESH KUMAR", "SHOBHA KUMARI"], "R": 16356}, {"C": ["R190810096646", "AMIT KUMAR RAY", "ARUN RAY", "PANO DEVI", 1], "R": 15844}, {"C": ["R190810096645", "SUDARSHAN KUMAR", "SHANKAR RISHIDEV", 13], "R": 16356}, {"C": ["R190810096644", "AMAN KUMAR PASWAN", "RUBEL PASWAN", "MOSHAMI DEVI"], "R": 16356}, {"C": ["R190810096643", "PRERNA BHARTI", 1, "SUBODH KUMAR SHARMA", "KALPANA BHARTI"], "R": 16352}, {"C": ["R190810096642", "AMIT KUMAR DAS", 0, "SONE LAL DAS", "ARUNA DEVI"], "R": 16352}, {"C": ["R190810096641", "GUDDU KUMAR", "GORE LAL MANDAL", "SUMITRA DEVI", 3], "R": 15844}, {"C": ["R190810096640", "SAMAN KUMAR", "RAMNATH SAH", "BHARTI DEVI", 0, 0], "R": 15812}, {"C": ["R190810096639", "Krishna Kumar Singh", "SANTOSH SINGH", "PARWATI DEVI"], "R": 16356}, {"C": ["R190810096638", "GAURAV KUMAR", "AMIR CHANDRA YADAV", "KALPANA DEVI"], "R": 16356}, {"C": ["R190810096637", "SHANKAR KUMAR", "ARUN BISHWAS", 69], "R": 16356}, {"C": ["R190810096636", "MOHIT KUMAR PARAS", "MARTUND KUMAR GOSWAMI", "SULEKHA DEVI", 2], "R": 15844}, {"C": ["R190810096635", "AMIT KUMAR SHARMA", "BIDUR SHARMA", 73, 0], "R": 15844}, {"C": ["R190810096634", "SIKANDAR SADA", "RAJENDRA SADA", "DURO DEVI", 1], "R": 15844}, {"C": ["R190810096633", "SK MUNNA", "SK UNUS", "ASIMA KHATUN", 2], "R": 15844}, {"C": ["R190810096632", "SANJEEV KUMAR", "BALRAM PRASAD", 97], "R": 16356}, {"C": ["R190810096631", "JYOTISH KUMAR", "MAKONI MANDAL", "BIJALI DEVI", 0], "R": 15844}, {"C": ["R190810096630", "VIKAS KUMAR MAHLI", "BALRAM MAHLI", 49, 3], "R": 15844}, {"C": ["R190810096629", 98, "BACHCHU SAH", 69, 0], "R": 15844}, {"C": ["R190810096628", "MITHUN KUMAR MANDAL", "BECHAN MANDAL", "ARUNA DEVI"], "R": 16356}, {"C": ["R190810096627", "ASHISH KUMAR", "MANOJ KUMAR", "DEVI RANI"], "R": 16356}, {"C": ["R190810096626", "VIKASH KUMAR PASWAN", "CHANDAN PASWAN", "RAJKUMARI DEVI", 1], "R": 15844}, {"C": ["R190810096625", "RAJKUMAR MAHALDAR", "CHETHAR MAHALDAR", "SIBO DEVI", 3], "R": 15844}, {"C": ["R190810096624", "AMITESH KUMAR BISHWAS", "RAJ KUMAR BISHWAS", "Sarita Devi", 0], "R": 15844}, {"C": ["R190810096623", "NEERAJ KUMAR YADAV", "DILIP KUMAR YADAV", 90], "R": 16356}, {"C": ["R190810096622", "RAHUL YADAV", "BINOD YADAV", "BIMLI DEVI"], "R": 16356}, {"C": ["R190810096621", "KARAN KUMAR PASWAN", "GOPAL PASWAN", "FAGUNI DEVI", 1], "R": 15844}, {"C": ["R190810096620", "MURARI  KUMAR", "BANARSI PRASAD SINGH", 31, 3], "R": 15844}, {"C": ["R190810096619", "NITISH KUMAR", "AMAR NATH CHOUDHARY", "JOSHANA DEVI", 0], "R": 15844}, {"C": ["R190810096618", "GURIYA KUMARI", 1, "GOVIND YADAV", "SUSHMA DEVI"], "R": 16352}, {"C": ["R190810096617", 31, 0, "RAM KUMAR MAHTO", "NANDANI DEVI"], "R": 16352}, {"C": ["R190810096616", "ANAY KUMAR", "AMOD YADAV", "RAJ KUMARI"], "R": 16356}, {"C": ["R190810096615", "ANUJ KUMAR JHA", "MAHESHWAR JHA", "NUTAN DEVI", 2], "R": 15844}, {"C": ["R190810096614", "SHEJAL CHANDRA", 1, "CHANDRAMOHAN MANDAL", "ANJULA DEVI", 0], "R": 15840}, {"C": ["R190810096613", "SHUBHAM KUMARI", "JAI NARAYAN SAH", "KAVITA DEVI"], "R": 16356}, {"C": ["R190810096612", "MANISH KUMAR RAJAK", 0, "GANESH RAJAK", "SHARMILA DEVI", 1], "R": 15840}, {"C": ["R190810096611", 5, "RAMLAL MAHTO", "GEETA DEVI", 0], "R": 15844}, {"C": ["R190810096610", "KISHAN KUMAR BARNWAL", "RANA PRASAD SAH", 16], "R": 16356}, {"C": ["R190810096609", "SUMIT KUMAR PODDAR", "GHANSHYAM PODDAR", "ASHA DEVI"], "R": 16356}, {"C": ["R190810096608", "SAGAR KUMAR SINGH", "SADANAND SINGH", "SANJO DEVI"], "R": 16356}, {"C": ["R190810096607", 21, "PRAMOD KUMAR THAKUR", "BINDU DEVI"], "R": 16356}, {"C": ["R190810096606", "SHANKAR KUMAR", "YOGENDRA PAL", 20], "R": 16356}, {"C": ["R190810096605", 62, "NARAYAN MANDAL", "PARVATI DEVI"], "R": 16356}, {"C": ["R190810096604", 21, "DILIP PASWAN", "ARTI DEVI", 1], "R": 15844}, {"C": ["R190810096603", "SUBODH KUMAR PRAMANIK", "RAKHAL CHANDRA PRAMANIK", 73, 0], "R": 15844}, {"C": ["R190810096602", "VIKKY KUMAR", "BARUN SINGH", "KALPANA DEVI"], "R": 16356}, {"C": ["R190810096601", "Shyam sunder kumar yadav", "LAKSHMAN KUMAR YADAV", 73], "R": 16356}, {"C": ["R190810096600", "SOWAN KUMAR NUNIA", "RAJ KUMAR NUNIA", "CHAITI DEVI"], "R": 16356}, {"C": ["R190810096599", "SHAMBHU KUMAR MAHALDAR", "NITAI MAHALDAR", "SULEKHA DEVI"], "R": 16356}, {"C": ["R190810096598", "NITISH KUMAR", "DEVNARAYAN MANDAL", "JAYMALA DEVI"], "R": 16356}, {"C": ["R190810096597", "BANTI KUMAR", "SHAMBHU NATH BISHWAS", 33], "R": 16356}, {"C": ["R190810096596", "GUDDU KUMAR YADAV", "AVDHESH YADAV", 31], "R": 16356}, {"C": ["R190810096595", "AMAN KUMAR PASWAN", "Arjun Paswan", 20, 1], "R": 15844}, {"C": ["R190810096594", "ANAND KUMAR SINGH", "GULAB PRASAD SINGH", "KASHTURI DEVI", 0], "R": 15844}, {"C": ["R190810096593", "NEERAJ KUMAR", "RAMPRAVESH SINGH", 33], "R": 16356}, {"C": ["R190810096592", "DIPAK KUMAR", "MANINDRA KUMAR MANDAL", 68], "R": 16356}, {"C": ["R190810096591", "RAJAN CHOUDHARY", "KAPILDEV CHOUDHARY", "MEERA DEVI"], "R": 16356}, {"C": ["R190810096590", "KETUL KUMAR MAHTO", "Jai Narayan Mahto", "HIRA DEVI"], "R": 16356}, {"C": ["R190810096589", "KASHISH RAJ", 1, "RAJ KUMAR SAH", "ARTI DEVI"], "R": 16352}, {"C": ["R190810096588", "AMOL KUMAR", 0, "LAXMI CHOUHAN", 73], "R": 16352}, {"C": ["R190810096587", "PANKAJ KUMAR RAY", "GOPAL RAY", "TARA DEVI"], "R": 16356}, {"C": ["R190810096586", "MD ALIRAJA", "MD MAJBUL", "RAKINA KHATUN"], "R": 16356}, {"C": ["R190810096585", "CHHOTU KUMAR", "BRAHMDEV MAHTO", 21], "R": 16356}, {"C": ["R190810096584", "SURAJ KUMAR", "SATYANARAYAN PRASAD SINGH", "MIRA DEVI"], "R": 16356}, {"C": ["R190810096583", "KUMOD KUMAR SAH", "NAND LAL SAH", "REENA DEVI"], "R": 16356}, {"C": ["R190810096582", "CHANDRASHEKHAR AJAD", "PRAMOD PANDIT", 69], "R": 16356}, {"C": ["R190810096581", "AMIT KUMAR", "KUMAR ASHOK", 90], "R": 16356}, {"C": ["R190810096580", "LAXMAN PANDIT", "SHRIPAT PANDIT", "CHAMELI DEVI"], "R": 16356}, {"C": ["R190810096579", "CHAMPAK KUMAR", "GAURI PRASAD YADAV", "RUSIA DEVI"], "R": 16356}, {"C": ["R190810096578", "SUNIL KUMAR SAH", "CHHOTE LAL SAH", 37], "R": 16356}, {"C": ["R190810096577", "SHRAWAN KUMAR", "RAMESHWAR PRASAD SINGH", "PREMSHILA DEVI"], "R": 16356}, {"C": ["R190810096576", "MANISH KUMAR", "SAGAR PRASAD MANDAL", "BELA DEVI"], "R": 16356}, {"C": ["R190810096575", "MANISH KUMAR GOSWAMI", "KISHOR GOSWAMI", 23], "R": 16356}, {"C": ["R190810096574", "ANANT KUMAR SINGH", "JAI SHANKAR SINGH", "HEMLATA SINGH"], "R": 16356}, {"C": ["R190810096573", "PURUSHOTTAM KUMAR", "SHIVSHANKAR MAHTO", "SARASWATI DEVI"], "R": 16356}, {"C": ["R190810096572", "PRABHAKAR KUMAR SHARMA", "AKSHAY SHARMA", "SUSHMA DEVI"], "R": 16356}, {"C": ["R190810096571", "AJIT KUMAR", "BALDEV SHARMA", 73], "R": 16356}, {"C": ["R190810096570", 98, "SRIKANT RAM", 18, 2, 22, 1], "R": 3812}, {"C": ["R190810096569", "PRINCE RAJ", "NAWAL KISHOR SHARMA", "JULI DEVI"], "R": 16356}, {"C": ["R190810096568", "MANOHAR KUMAR", "KARU PASWAN", "LALTI DEVI", 7, 1, 12, 1, 23, 0], "R": 3204}, {"C": ["R190810096567", "dhananjay kumar", "RAMBALI RAY", "BUDHIYA DEVI", 0], "R": 15844}, {"C": ["R190810096566", "SHEKHAR KUMAR SAH", "VIJAY SAH", 36, 0, 0, 17, 0], "R": 11908}, {"C": ["R190810096565", "CHANDAN KUMAR SAH", "YOGESH CHANDRA SAH", "SULEKHA DEVI"], "R": 16356}, {"C": ["R190810096564", "RAJIV KUMAR CHOUDHARY", "WAKIL CHOUDHARY", "PRAMILA DEVI", 1], "R": 15844}, {"C": ["R190810096563", "SARVESH KUMAR", "RAVINDRA NATH DAS", "SANYUKTA DEVI", 2], "R": 15844}, {"C": ["R190810096562", 0, "SURESH PASWAN", 12, 1], "R": 15844}, {"C": ["R190810096561", 1, "GYANDEV PRASAD", "RAKHI DEVI"], "R": 16356}, {"C": ["R190810096560", "CHAITANYA KUMAR RAY", "MANTU RAY", "YSHODA DEVI"], "R": 16356}, {"C": ["R190810096559", "MOHIT KUMAR", "RAJEEV KUMAR", "REENA DEVI"], "R": 16356}, {"C": ["R190810096558", "SOURAV KUMAR", "RANJEET KUMAR PASWAN", 18], "R": 16356}, {"C": ["R190810096557", "RESHAV RAJ", "GANESH PASWAN", "JABA DEVI"], "R": 16356}, {"C": ["R190810096556", "NEHA KUMARI", 1, "SUDHIR RAM", "PUNAM DEVI"], "R": 16352}, {"C": ["R190810096555", "BRAJNANDAN JHA", 0, "SHYAMAKANT JHA", "RUBY DEVI", 2], "R": 15840}, {"C": ["R190810096554", "MUKESH KUMAR", "MADAN TATMA", 73, 1], "R": 15844}, {"C": ["R190810096553", "RAJ KUMAR RAJAK", "SUBOL RAJAK", "MEERA DEVI"], "R": 16356}, {"C": ["R190810096552", "JITENDRA KUMAR SINGH", "NAVAL KISHOR SINGH", "BIJALEE DEVI", 2], "R": 15844}, {"C": ["R190810096551", "ADARSH KUMAR", "SRINIVAS SINGH", 12], "R": 16356}, {"C": ["R190810096550", "PRASANNDEEP KUMAR SINGH", "CHANDRADEEP SINGH", "REETA DEVI"], "R": 16356}, {"C": ["R190810096549", "ALOK ANAND", "BIBHASH CHANDRA MISHRA", "HEMLATA MISHRA"], "R": 16356}, {"C": ["R190810096548", "GUNJAN KUMAR", "BALIRAM SINGH", 90], "R": 16356}, {"C": ["R190810096547", "NIKHAR KUMAR SINGH", "MANIKANT SINGH", "LUCY DEVI"], "R": 16356}, {"C": ["R190810096546", "MUKESH KUMAR KUSHWAHA", "SHREE RAM KUSHWAHA", 56, 5, 0], "R": 15812}, {"C": ["R190810096545", "SUMIT KUMAR RAJAK", "BHUPESH RAJAK", "PUNAM DEVI", 1], "R": 15844}, {"C": ["R190810096544", "Kumari kajal", 1, "DEO KUMAR ANAND", 0], "R": 15856}, {"C": ["R190810096543", "SAJAN KUMAR YADAV", 0, "VILASH YADAV", "DHARMI DEVI"], "R": 16352}, {"C": ["R190810096542", "PRINCE PRIY", "ARJUN KUMAR", "NAVITA KUMARI"], "R": 16356}, {"C": ["R190810096541", "RAVINDAR KUMAR MANDAL", "NARAYAN MANDAL", "JICHHA DEVI", 3], "R": 15844}, {"C": ["R190810096540", "Chandan Kumar Singh", "SANJAY KUMAR SINGH", 56, 0], "R": 15844}, {"C": ["R190810096539", "RAMAN YADAV", "RAMBACHAN YADAV", "PUSHPA DEVI"], "R": 16356}, {"C": ["R190810096538", "MANINDAR KUMAR", "NAGENDRA SINGH", 11], "R": 16356}, {"C": ["R190810096537", "SUJEET KUMAR SAHANI", "SUBHASH SAHANI", "REETA DEVI"], "R": 16356}, {"C": ["R190810096536", "VICKY KUMAR RAJAK", "SANJAY RAJAK", 52, 1], "R": 15844}, {"C": ["R190810096535", "CHHOTU RAVIDAS", "MULENDRA RAVIDAS", "RANJO DEVI"], "R": 16356}, {"C": ["R190810096534", 41, "NAVIN SAH", 56, 0], "R": 15844}, {"C": ["R190810096533", "SUMIT KUMAR", "BHAGWAN SHARMA", "NIMPAL DEVI"], "R": 16356}, {"C": ["R190810096532", "Chandan Kumar Singh", "AJAY KUMAR SINGH", "CHHAYA DEVI", 2], "R": 15844}, {"C": ["R190810096531", "SANDEEP KUMAR SINGH", "VINOD SINGH", "JYOTI DEVI"], "R": 16356}, {"C": ["R190810096530", 94, "SIKANDER SINGH", 38, 0], "R": 15844}, {"C": ["R190810096529", "SHIVAM KUMAR", "SHAMBHU RAJAK", 36, 1], "R": 15844}, {"C": ["R190810096528", "RAVINDRA KUMAR", "SHRI KANT MANDAL", "NAMITA DEVI", 0], "R": 15844}, {"C": ["R190810096527", 98, "RAJKISHOR SUMAN", "CHULHO DEVI"], "R": 16356}, {"C": ["R190810096526", "ROUSHAN KUMAR", "MAHESH PRASAD GUPTA", 18], "R": 16356}, {"C": ["R190810096525", "SANJAY TUDU", "ARJUN TUDU", "BARKI MURMU", 3], "R": 15844}, {"C": ["R190810096524", "RAJAN KUMAR SINGH", "RAJDHAR SINGH", 56, 2], "R": 15844}, {"C": ["R190810096523", "MD TALIB", "MD. RASID", "SABERA KHATOON", 0], "R": 15844}, {"C": ["R190810096522", "SABBIR ALAM", "ABDUL MATIN", "NILUFA KHATUN"], "R": 16356}, {"C": ["R190810096521", "MD MAZID", "MD. SHAHID", "SHABNAM ARA"], "R": 16356}, {"C": ["R190810096520", "VIVEK KUMAR SAH", "DILIP KUMAR SAH", 21], "R": 16356}, {"C": ["R190810096519", "NIKKI KUMAR SHARMA", "NARAD SHARMA", 97], "R": 16356}, {"C": ["R190810096518", 98, "GOPAL DAS", "RUNA DEVI"], "R": 16356}, {"C": ["R190810096517", "SHEKHAR KUMAR RAVIDAS", "RAJ KUMAR RAVIDAS", 49, 1], "R": 15844}, {"C": ["R190810096516", "DEVRISHI SAH", "ARJUN KUMAR SAH", "MALA DEVI", 0], "R": 15844}, {"C": ["R190810096515", "PANKAJ KUMAR MAHTO", "RAM PRAWESH MAHTO", 15], "R": 16356}, {"C": ["R190810096514", "NIRAJ KUMAR YADAV", "TAEESHAR YADAV", "BEENA DEVI"], "R": 16356}, {"C": ["R190810096513", "ASHAFAQUE ALAM", "WAHAB ALI", "ROMISA KHATOON"], "R": 16356}, {"C": ["R190810096512", "ANKIT KUMAR SINGH", "RANJIT SINGH", 18], "R": 16356}, {"C": ["R190810096511", "DHIRAJ KUMAR", "DILIP MANDAL", 52], "R": 16356}, {"C": ["R190810096510", "BHAJAN LAL SHARMA", "BANWARI SHARMA", 69], "R": 16356}, {"C": ["R190810096509", "RAUNAK KUMAR", "KHAGESH MANDAL", "KALPANA DEVI"], "R": 16356}, {"C": ["R190810096508", "RAHUL KUMAR JHA", "MANOJ KUMAR JHA", "SHAIL DEVI", 2], "R": 15844}, {"C": ["R190810096507", "MD ASLAM", "MD ASGAR", "SAHIDA KHATUN", 0], "R": 15844}, {"C": ["R190810096506", "DIPANSHU KUMAR", "SHIV KUMAR SINGH", 12, 2], "R": 15844}, {"C": ["R190810096505", "CHITRANJAN KUMAR", "KHAGESH MANDAL", "KALPANA DEVI", 0], "R": 15844}, {"C": ["R190810096504", 64, "SUBODH YADAV", "PUNAM DEVI"], "R": 16356}, {"C": ["R190810096503", "BEBI KUMARI", 1, "SHRAWAN PANDIT", "CHANDMUNI DEVI", 0, 14, 24, 1], "R": 3776}, {"C": ["R190810096502", 31, 0, "RANJEET PRASAD", "NITU DEVI"], "R": 16352}, {"C": ["R190810096501", "MD MOBIN AZAD", "MD. TOHID", "SHAHIDA KHATOON", 5, 17, 2, 0, 0], "R": 3268}, {"C": ["R190810096500", "VIKRANT VIJAY", "KUNDAN KUMAR PATEL", "Reena Kumari", 0], "R": 15844}, {"C": ["R190810096499", "Vikram kumar", "RAJU YADAV", 46], "R": 16356}, {"C": ["R190810096498", "RUDAL KUMAR MANDAL", "BHAVESH MANDAL", "MALA DEVI"], "R": 16356}, {"C": ["R190810096497", 7, "DOMAN RAY", "LAKSHMI DEVI"], "R": 16356}, {"C": ["R190810096496", "VISHAL KUMAR SHARMA", "Mantu Sharma", 74], "R": 16356}, {"C": ["R190810096495", 51, "RAJ KUMAR CHOUDHARY", "CHAMCHAM KUMARI", 2], "R": 15844}, {"C": ["R190810096494", "DEEPAK KUMAR DAS", "SHIV NARAYAN DAS", 46, 1], "R": 15844}, {"C": ["R190810096493", "VISHWJEET KUMAR", "MANOJ SINGH", 0], "R": 15860}, {"C": ["R190810096492", "SUJEET KUMAR THAKUR", "SANJAY THAKUR", "MUNNI DEVI"], "R": 16356}, {"C": ["R190810096491", "BADAL KUMAR YADAV", "RAJEEV KUMAR YADAV", "TILA DEVI"], "R": 16356}, {"C": ["R190810096490", "RAJA KUMAR", "DILIP MANDAL", "Parul Devi"], "R": 16356}, {"C": ["R190810096489", "SHIVAM KUMAR", "KRISHAN KUMAR", 47], "R": 16356}, {"C": ["R190810096488", "GURUTTAM KUMAR", "VIJAY YADAV", 40], "R": 16356}, {"C": ["R190810096487", "ARUN KUMAR MANDAL", "DINESH MANDAL", 33], "R": 16356}, {"C": ["R190810096486", "SANJAY KUMAR MAHTO", "NANKI MAHTO", "TARA DEVI"], "R": 16356}, {"C": ["R190810096485", "SHIVAM KUMAR", "ASHOK KUMAR YADAV", "GEETA DEVI"], "R": 16356}, {"C": ["R190810096484", "NITISH KUMAR BHARTI", "GULAB CHAND YADAV", "CHANDANA DEVI"], "R": 16356}, {"C": ["R190810096483", "KARAN KUMAR VISHWAS", "SINHESHWAR VISHWAS", "BEBI DEVI"], "R": 16356}, {"C": ["R190810096482", "GOVIND KUMAR KUSHWAHA", "RAMKALYAN MAHTO", "MIRA DEVI"], "R": 16356}, {"C": ["R190810096481", "SHASHI RANJAN KUMAR", "SHYAM LAL MANDAL", 73], "R": 16356}, {"C": ["R190810096480", "PALLAVI KUMARI", 1, "RAJESH  KUMAR SAH", 66], "R": 16352}, {"C": ["R190810096479", "RANI KUMARI", "RAMDEV PODDAR", 21], "R": 16356}, {"C": ["R190810096478", 23, 0, "SIKANDAR PANDIT", "SULEKHA DEVI"], "R": 16352}, {"C": ["R190810096477", "SHIVAM  KUMAR", "PANKAJ KUMAR GUPTA", "SUDHA DEVI"], "R": 16356}, {"C": ["R190810096476", "SANJAY KUMAR THAKUR", "DHIREN THAKUR", "BIMLA DEVI"], "R": 16356}, {"C": ["R190810096475", "PREETAM KUMAR", "SHIV SHANKAR MEHTA", "SARASWATI DEVI"], "R": 16356}, {"C": ["R190810096474", "DIPU KUMAR", "PRAVIN KUMAR SINGH", 18], "R": 16356}, {"C": ["R190810096473", "VISHWANATH KUMAR MANDAL", "MOHAN MANDAL", 73], "R": 16356}, {"C": ["R190810096472", "AJEET KUMAR", "DILIP MAHTO"], "R": 16372}, {"C": ["R190810096471", "JITENDRA KUMAR SINGH", "PRABHU NARAYAN SINGH", 49], "R": 16356}, {"C": ["R190810096470", "RAJA KUMAR", "MAHESH PRASAD GUPTA", 46], "R": 16356}, {"C": ["R190810096469", "VIPIN KUMAR", "PARMA NAND MANDAL", 12], "R": 16356}, {"C": ["R190810096468", "SURYANARAYAN YADAV", "GOPAL YADAV", "SULEKHA DEVI"], "R": 16356}, {"C": ["R190810096467", "AMIT KUMAR", "CHHATTU MANDAL", 46], "R": 16356}, {"C": ["R190810096466", "RINTU AZAD", "AZAD PRASAD MANDAL", "SAVITA DEVI"], "R": 16356}, {"C": ["R190810096465", "GOPAL KUMAR", "RANJAN CHOUHAN", "BINDI DEVI"], "R": 16356}, {"C": ["R190810096464", "AMAR KUMAR DAS", "PRAMANAND DAS", "PURNI DEVI", 1], "R": 15844}, {"C": ["R190810096463", "MONU MANDAL", "NARESH MANDAL", "SAVITA DEVI", 3], "R": 15844}, {"C": ["R190810096462", 73, "RAMESH PRASAD TANTI", "PARWATI DEVI", 1], "R": 15844}, {"C": ["R190810096461", "AMIT KUMAR", "AMBIKA PRASAD", "SUNITA", 0, 2, 0, 25, 1], "R": 3268}, {"C": ["R190810096460", "NISHCHAY KUMAR", "MADAN PRASAD", "CHANCHALA DEVI"], "R": 16356}, {"C": ["R190810096459", "AVINASH KUMAR", "AJAY SINGH", "KAMLA DEVI", 2], "R": 15844}, {"C": ["R190810096458", 37, "SURENDRA PARSHAD", 56, 0], "R": 15844}, {"C": ["R190810096457", "RANJAY KUMAR", "VINOD PRASAD YADAV", 31], "R": 16356}, {"C": ["R190810096456", "PAVAN KUMAR", "BINOD YADAV"], "R": 16372}, {"C": ["R190810096455", "ADITYA", "RAJ KISHOR", "ASMITA SINGH", 2], "R": 15844}, {"C": ["R190810096454", "ANSHU KUMARI", 1], "R": 16376}, {"C": ["R190810096453", 88, 0, "ARUN PRASAD", "SINDHU DEVI", 0], "R": 15840}, {"C": ["R190810096452", "ALOK KUMAR", "BABULAL PRASAD", "MITU DEVI"], "R": 16356}, {"C": ["R190810096451", "CHOTELAL PANDEY", "MITHILESH PANDEY", 15, 2], "R": 15844}, {"C": ["R190810096450", "KUNDAN RAJ", "AKHILESH PRASAD", "GAYTRI DEVI", 0], "R": 15844}, {"C": ["R190810096449", "JITENDRA KUMAR", "BHOLA CHAUDHARI", 73, 1], "R": 15844}, {"C": ["R190810096448", "KAUSHAL KUMAR CHAUDHARY", "KRISHAN CHAUDHARY", "SARSVATI DEVI"], "R": 16356}, {"C": ["R190810096447", 98, "RANJIT SAW", 31, 0], "R": 15844}, {"C": ["R190810096446", "SURENDRA KUMAR", "RAJENDRA PRASAD", "MUNNI DEVI"], "R": 16356}, {"C": ["R190810096445", "MANISH KUMAR", "SHIV SHANKER PRASAD", "Asha Sinha", 2], "R": 15844}, {"C": ["R190810096444", 65, "KAPILDEV PARSAD YADAV", 13, 0], "R": 15844}, {"C": ["R190810096443", "AKASH CHANDRA", "VIJAY CHAUDHARY", "BABITA BHARTI", 1], "R": 15844}, {"C": ["R190810096442", "PINTU KUMAR", "RAMJI CHAUHAN", 18, 0], "R": 15844}, {"C": ["R190810096441", 56, "SANJEET CHAUDHARY", "SHANTI DEVI", 1], "R": 15844}, {"C": ["R190810096440", "SUDHIR KUMAR", "JAGDISH YADAV", "SARIFA DEVI", 0], "R": 15844}, {"C": ["R190810096439", 23, "SUDHEER YADAV", "Hirda Devi"], "R": 16356}, {"C": ["R190810096438", 62, "SANJAY YADAV", 38], "R": 16356}]}], "IC": false, "RT": [["'R190810096438'", "'SACHIN KUMAR'", "'M'", "'SANJAY YADAV'", "'REKHA DEVI'", "'Electrician (NSQF)'", "'2 Year'", "'BIHAR'", "'NAWADA'", "'OBC'", "'10th'", "'Engineering'", "'Kumar ITC'", "'P'"]], "ValueDicts": {"D0": ["R190810097437", "R190810097436", "R190810097435", "R190810097434", "R190810097433", "R190810097432", "R190810097431", "R190810097430", "R190810097429", "R190810097428", "R190810097427", "R190810097426", "R190810097425", "R190810097424", "R190810097423", "R190810097422", "R190810097421", "R190810097420", "R190810097419", "R190810097418", "R190810097417", "R190810097416", "R190810097415", "R190810097414", "R190810097413", "R190810097412", "R190810097411", "R190810097410", "R190810097409", "R190810097408", "R190810097407", "R190810097406", "R190810097405", "R190810097404", "R190810097403", "R190810097402", "R190810097401", "R190810097400", "R190810097399", "R190810097398", "R190810097397", "R190810097396", "R190810097395", "R190810097394", "R190810097393", "R190810097392", "R190810097391", "R190810097390", "R190810097389", "R190810097388", "R190810097387", "R190810097386", "R190810097385", "R190810097384", "R190810097383", "R190810097382", "R190810097381", "R190810097380", "R190810097379", "R190810097378", "R190810097377", "R190810097376", "R190810097375", "R190810097374", "R190810097373", "R190810097372", "R190810097371", "R190810097370", "R190810097369", "R190810097368", "R190810097367", "R190810097366", "R190810097365", "R190810097364", "R190810097363", "R190810097362", "R190810097361", "R190810097360", "R190810097359", "R190810097358", "R190810097357", "R190810097356", "R190810097355", "R190810097354", "R190810097353", "R190810097352", "R190810097351", "R190810097350", "R190810097349", "R190810097348", "R190810097347", "R190810097346", "R190810097345", "R190810097344", "R190810097343", "R190810097342", "R190810097341", "R190810097340", "R190810097339", "R190810097338"], "D1": ["RAJU KUMAR", "ROHIT KUMAR", "MUNDRIKA KUMAR DAS", "MD ZAHIRUDDIN", "RITU KUMARI", "NAVEEN KUMAR", "NAVIN KUMAR", "SANTOSH KUMAR", "HARI OM KUMAR", "MANOJ KUMAR", "AJAY KUMAR", "RAMASHANKAR KUMAR", "SATYENDRA KUMAR", "NISHANT KUMAR", "SUMAN KUMAR LAL", "Ramesh Kumar", "OM PRAKASH BAITHA", "RAM NARAYAN KHATAWE", "FUL KUMARI", "KISHU KR JHA", "MINTU JHA", "ABHISHEK KUMAR", "Munna kumar", "RAHUL KUMAR", "JAGANNATH KUMAR", "PRATIMA KUMARI", "MADAN KUMAR", "RAM NARESH KUMAR", "PAPPU KUMAR", "LOVE KUMAR", "CHANDAN KUMAR", "PRINCE KUMAR", "SAROJ KUMAR", "SINTU KUMAR", "YUGESH KUMAR", "VIKAS KUMAR", "PRATIK KUMAR", "RAJESH KUMAR", "MINTU KUMAR", "CHAMAN KUMAR", "UMASHANKAR KUMAR", "GAUTAM KUMAR", "RAMESHWAR KUMAR", "PASHURAM KUMAR", "BIPIN SAH", "NIKETAN KUMAR", "SAPANA KUMARI", "VIKI KUMAR RAM", "KUNDAN KUMAR", "RAJU DAS", "ARUN KUMAR", "RAUSHAN KUMAR", "RAKESH RAM", "KAMLESH KUMAR", "MADHURI KUMARI", "VIJAY KUMAR SINGH", "RAVI KUMAR", "PRASHANT KUMAR", "AMRESH KUMAR", "RAHUL RAM", "DAYANAND KUMAR", "AVINISH KUMAR", "SACHIN KUMAR", "PREM KUMAR", "BIPIN KUMAR", "BABLU KUMAR", "LAXMI NARAYAN KUMAR", "RAMJEE KUMAR", "ASHISH RANJAN", "NISHA KUMARI", "RAMAN KUMAR", "SUNIL KUMAR", "RAVIKAR LAL", "VIVEK KUMAR", "SATISH KUMAR", "SHIVAM SHARMA", "SURESH KUMAR", "PRAVEEN KUMAR", "RAJAN RAJ", "SUSHANT KUMAR", "UMESH KUMAR", "CHANCHAL KUMAR", "KAMALJEET KUMAR", "RAJEEV KUMAR", "HARISH KUMAR", "KESHAV KUMAR", "AVINASH RAJ", "GAUTAM ANAND", "AMAN KUMAR", "VISHAL KUMAR", "GOLU KUMAR", "ASHISH RAJ", "TEJASH KUMAR", "BIRU KUMAR", "SONU KUMAR", "UDAY KUMAR", "SUJEET KUMAR", "SHISHUPAL KUMAR", "VIKASH KUMAR", "CHANDAN SHARMA"], "D2": ["M", "F"], "D3": ["RAMBIR SINGH", "SIYANANDAN BAITHA", "PARBHU DAS", "MD ANVARUL HAQUE", "GANESH SAH", "YOGENDRA SINGH", "RAJENDRA SINGH", "SHIVJEE SAHNI", "SUNIL MAHTO", "Ram Chandra Sah", "NARAYAN SAH", "RAMCHHAVILA SAH", "RADHE SHYAM SAH", "MADAN MAHTO", "LAL BABU PRASAD YADAV", "CHANDESHWAR PANDIT", "JAGESHWAR BAITHA", "SHIVJI BAITHA", "GARATI KHATAWE", "SURENDRA KUMAR SAH", "SARWADANAND JHA", "PARASURAM JHA", "GAGANDEV SINGH", "BINDALAL SINGH", "SHIV BALAK SAH", "BRAHAMDEV SAH", "MUSAFIR MAHTO", "RAM KUMAR SAH", "BILOCHI RAUT", "PRABHANS MANJHI", "RAM NATH RAY", "KAUSHAL PATEL", "RAMESH MISHRA", "RAMPHAL SAHNI", "SUBODH KUMAR", "BRIJLAL SAH", "KAUSHAL PASWAN", "HARINATH PRASAD PATWA", "NAGESHVAR RAY", "BIKAU THAKUR", "HARISHCHANDRA MAHTO", "SHIV SHARAN SHARMA", "KANHAI PRASAD YADAV", "BHARAT MISHRA", "Satyanarayan Mahto", "ARUN MISHRA", "HARISHANKAR KUMAR CHAUDHARY", "ARUN KUMAR THAKUR", "DEVENDRA KUMAR", "VIGAN RAM", "AMAR NATH PRASAD", "RAMPRAVESH BAITHA", "PRAHLAD DAS", "SHAMBHU DAS", "JAYKARAN SINGH", "BIRENDRA RAM", "LAXMI DAS", "SURESH SINGH", "Dilip Kumar", "RAGHAVENDRA BAITHA", "ASHOK KUMAR RAY", "SURESH KAPAR", "SURESH RAM", "SURESH MAHTO", "RAMBABU SAH", "Shatrudhan Thakur", "KAPILDEV SAH", "SHAMBHU PANDIT", "SIKINDAR YADAV", "SHATRUGHNA MAHTO", "RAM BHAROSH SAH", "RAM KAILASH RAY", "AJAY KUMAR MISHRA", "AMAR SAH", "UPENDRA PASWAN", "INDAL MAHTO", "UPENDRA PRASAD", "LALBABU BAITHA", "SIYALAL RAM", "Kaushal Kishore Thakur", "SANJAY PURVE", "RAMNARAYAN MAHTO", "SATYENDRA SHARMA", "MAHESH MAHTO", "VIRENDRA SAH", "MAHESH SAH", "RAM BALAK SAH", "SANJEEV KUMAR GUPTA", "GORAKH PASWAN", "RAMCHANDRA MAHTO", "LALITESHWAR JHA", "DILIP RAM", "JITENDRA SAH", "SANJAY PANDIT", "RAMREKHA SINGH", "BABUCHAND PANDIT", "PAPPU PRASAD", "NITYANAND SHARMA", "DAULAT RAY", "RAJBALLAM PRASAD"], "D4": ["NANDNI DEVI", "RINA DEVI", "SIKILIYA DEVI", "MAIFUL KHATOON", "PAVAN DEVI", "SUNAINA DEVI", "KULI DEVI", "Dulari devi", "VINITA DEVI", "RAM KUMARI DEVI", "SHANKUTLA DEVI", "URMILA DEVI", "MANJU DEVI", "MEENA DEVI", "RUPKALA DEVI", "Gita Devi", "SEEMA DEVI", "CHHOTI DEVI", "RITA DEVI", "BUDHANI DEVI", "PINKI DEVI", "LALITA DEVI", "TULSI DEVI", "SITA DEVI", "RUPKALI DEVI", "MUNESHVARI DEVI", "KAUSHALYA DEVI", "AASHA DEVI", "GONAURI DEVI", "MUNCHUN DEVI", "LEELA DEVI", "USHA DEVI", "JIBACHHI DEVI", "ANITA DEVI", "SHIVDULARI DEVI", "DEVANTI DEVI", "NIRMALA DEVI", "SANJHA DEVI", "REKHA DEVI", "Bindeshwari Devi", "SANGITA DEVI", "INDRA DEVI", "BABITA JAISWAL", "GAYATRI DEVI", "PUSPA DEVI", "SAVITRI DEVI", "RENU DEVI", "KANCHAN DEVI", "RAMPARI DEVI", "MINA DEVI", "DIMPI DEVI", "GULEBIYA DEVI", "CHANDA DEVI", "BACHCHI DEVI", "POONAM DEVI", "DIPIYA DEVI", "KIRAN DEVI", "SHAKILA DEVI", "RAJO DEVI", "PAWITRI DEVI", "MANJOO DEVI", "BANARASI DEVI", "PUSHPA MISHRA", "RINKU DEVI", "FULO DEVI", "KALSHIYA DEVI", "Veena Devi", "SHUSHILA DEVI", "SHOBHA DEVI", "SHILA DEVI", "POONAM SHARMA", "RAMKUMARI DEVI", "SHAKUNTALA DEVI", "SUNITA DEVI", "SUSHILA DEVI", "SRIPATI DEVI", "SUDHIRA JHA", "SUMAN DEVI", "SHAKINA DEVI", "RAJMANI DEVI", "ANJANI DEVI", "SUNITI SHARMA", "MINI DEVI", "NIRU DEVI", "PARBHA DEVI", "LALMUNI DEVI", "SUDAMIYA DEVI", "MINTU DEVI", "ASHARFI DEVI", "KANTI DEVI", "BABY DEVI", "SUNDARI DEVI", "SHARDHA DEVI", "LAL KESARI DEVI", "SANJU DEVI", "AMRAWATI DEVI", "ANJU KUMARI", "RANJU DEVI", "RAJIYA SULTANA", "RAMAWATI DEVI"], "D5": ["Electrician (NSQF)", "Wireman (NSQF)", "Welder (NSQF)", "Turner (NSQF)", "Foundryman (NSQF)", "Fitter (NSQF)", "Information Communication Technology System Maintenance (NSQF)", "Mechanic Diesel (NSQF)", "Mechanic (Motor Vehicle) (NSQF)", "Machinist (NSQF)", "Mechanic (Tractor) (NSQF)", "Electronics Mechanic (NSQF)"], "D6": ["2 Year", "1 Year"], "D7": ["BIHAR"], "D8": ["SITAMARHI", "JEHANABAD", "NAWADA", "PATNA", "MUZAFFARPUR", "BANKA", "AURANGABAD", "VAISHALI", "PURBA CHAMPARAN", "BUXAR", "SARAN", "ROHTAS", "GAYA", "KAIMUR (BHABUA)", "NALANDA", "MUNGER", "CHAPRA", "KATIHAR"], "D9": ["OBC", "SC", "GEN", "ST"], "D10": ["10th", "12th"], "D11": ["Engineering"], "D12": ["Govt Industrial Training Institute", "Omkar Pvt.Iti", "J.P.S Private ITI", "UNIVERSAL PRIVATE ITI", "Govt.Industrial Training Institute for Women", "Bhavani Private ITI", "Adharsh Industrial Training Centre", "Maa Private ITI", "Government Industrial Training Institute", "Maharshi Vishva Mitra ITC", "Pahalwan Paras Private ITI", "Bharat Private ITI", "Pandit Brahmdev Private ITI", "Gurukul Private ITI", "Shaheed Pramod ITC,", "Gyandeep Private ITI-QCI", "Gilani Private Industrial Training Institute", "SS IMPERIAL PRIVATE ITI", "Gita Private ITI", "Kabeer Private ITI, Buxar", "Sushil Vidya  ITC", "Dr. Rajendra Prasad ITC", "DML PRIVATE ITI", "GOVT. I.T.I. MAHKAR GAYA", "Raghuni Ramakant Private ITI", "Kumar ITC"], "D13": ["G", "P"]}}]}}}}]}